{"exams":[{"id":"tdl4358z","name":"DS 05","exercises":[{"id":"fev0gjne","title":"Exercice 1 : Hauts-parleurs","questions":[{"id":"55yukdid","label":"A.1","competences":["N","V","R"],"items":[{"id":"507h6qdb","label":"OdG correct pour le woofer","points":0.5},{"id":"y66u2h7e","label":"OdG correct pour le tweeter","points":0.5}]},{"id":"9hn1vj87","label":"A.2","competences":["N","V"],"items":[{"id":"lzhrlfua","label":"Calcul de Rb d'après la puissance","points":2},{"id":"wqz4usbe","label":"Valeur de L","points":0.5},{"id":"47ljzdg8","label":"Valeur de C","points":0.5}],"bonus":false},{"id":"awsnqs09","label":"B.1","competences":["N"],"items":[{"id":"oijcz4e8","label":"Analyse correcte pour un des deux circuits","points":1.5},{"id":"sdyxylhq","label":"Identification correcte (si justifiée même approximativement)","points":0.5}]},{"id":"06nuka5q","label":"B.2","competences":["R"],"items":[{"id":"0eegwxql","label":"Valeur de n justifiée et correcte","points":2}]},{"id":"0m5yzvkt","label":"B.3","competences":["R"],"items":[{"id":"5oczvu25","label":"Calcul du module","points":1},{"id":"npucjsxi","label":"Identification","points":1}]},{"id":"32pzdqqp","label":"B.4","competences":["R"],"items":[{"id":"w6to2wwr","label":"Calcul du module","points":1},{"id":"1b57sf5o","label":"Identification","points":3}],"bonus":false}],"coeff":1},{"id":"rwrad6j8","title":"Exercice 2 : Portée d'un lancer","questions":[{"id":"y3sg56lx","label":"A.1","competences":["A"],"items":[{"id":"5jixnhaz","label":"Définition du référentiel galiléen","points":0.5},{"id":"24qbxv18","label":"Condition sur la durée de l'expérience","points":0.5}]},{"id":"nwsf9pes","label":"A.2","competences":["R"],"items":[{"id":"crik6b73","label":"Référentiel, système, BdF (correct !)","points":0.5},{"id":"4owexrnb","label":"Equations du mouvement correctes","points":1},{"id":"9hausbej","label":"Absence d'accélération suivant z","points":0.5}]},{"id":"5vgh9ai4","label":"A.3","competences":["R"],"items":[{"id":"64yvr5uh","label":"Trajectoire établie","points":1},{"id":"0h44m53n","label":"Forme","points":0.5},{"id":"a1t5kvrl","label":"Symétrie","points":0.5}]},{"id":"ocfrtp1v","label":"A.4","competences":["R","N"],"items":[{"id":"afwmc9g5","label":"Condition sur l'annulation de la vitesse // propriétés géométriques de la parabole","points":0.5},{"id":"8c6yq3kg","label":"Coordonnées correctes","points":1},{"id":"898c7d5x","label":"Définition de la portée","points":1},{"id":"ejkd89o8","label":"Calcul","points":0.5}]},{"id":"2n64gszw","label":"B.1","competences":["N","R","V"],"items":[{"id":"fhhx1cha","label":"Dimension alpha correcte","points":0.5},{"id":"7hcfqp9x","label":"tau etabli par analyse dimensionnelle","points":1},{"id":"ju3qxgji","label":"Mouvement toujours plan","points":0.5}]},{"id":"ypsev6fy","label":"B.2","competences":["R"],"items":[{"id":"14gu1btu","label":"Nouveau bilan des forces","points":0.5},{"id":"k2h1nkw9","label":"PFD bien posé","points":0.5},{"id":"ed8ag4zc","label":"Vitesse correcte","points":1.5},{"id":"c1gvhv4o","label":"Position correcte","points":1.5}]},{"id":"bux35oit","label":"B.4","competences":["R"],"items":[{"id":"d8siusny","label":"Passage à la limite","points":0.5},{"id":"8fkni8cd","label":"Identification de vlim","points":0.5},{"id":"xg8nykmv","label":"Déf de la portée","points":0.5},{"id":"3klmivf1","label":"Détermination de la portée","points":0.5}]},{"id":"rokk8ye2","label":"B.5","competences":["N","V"],"items":[{"id":"pq8drcrt","label":"Allure de Tartaglia","points":1.5},{"id":"8wqogyuv","label":"Phases bien séparées","points":0.5}]},{"id":"9tafd606","label":"B.6","competences":["N","V"],"items":[{"id":"3u2k3d8x","label":"Bonne allure","points":1}]},{"id":"sr75c1mm","label":"B.7","competences":["R"],"items":[{"id":"9wrqnjc0","label":"Etude de la dérivée Ok","points":1},{"id":"dkneh8h5","label":"Détermination de beta","points":1}]},{"id":"yf6n8api","label":"B.8","competences":["V"],"items":[{"id":"zfinlior","label":"Justification (graphique ou calculatoire)","points":1}]},{"id":"trysfn1h","label":"B.9","competences":["A"],"items":[{"id":"c4357fs1","label":"Linéarisation juste","points":2},{"id":"5w280aq9","label":"Boucle de calcul juste (longueur de la boucle, variables définies...)","points":2},{"id":"53xrkw14","label":"Graphique tracé et correct","points":1}]},{"id":"ok2syrrk","label":"10","competences":["R"],"items":[{"id":"pjcwjaq6","label":"Expression correcte","points":1}]},{"id":"4hxyhek9","label":"12","competences":["N"],"items":[{"id":"4ev72tkb","label":"Lien remarqué avec la portée","points":1},{"id":"oyznc9l3","label":"Application correcte de la formule donnée","points":1}]},{"id":"bvt823zv","label":"13","competences":["N"],"items":[{"id":"l5qgjqgl","label":"Explication","points":1},{"id":"4gyldfz3","label":"Intrevalle","points":1}]},{"id":"sc5aq7sl","label":"14","competences":["R"],"items":[{"id":"qk0csnw1","label":"Expression de la portée sans simplification","points":0.5},{"id":"9pp1lg75","label":"Exploitation de l'égalité donnée par l'énoncé","points":2},{"id":"hjwhgm38","label":"Aboutissement du calcul","points":0.5}]}]},{"id":"x36t1qsj","title":"Exercice 3 : Système récupérateur d'énergie","questions":[{"id":"drgof1xu","label":"A.1","competences":["A"],"items":[{"id":"7juj0kaq","label":"Loi de Hooke correcte","points":1}]},{"id":"lxg44keb","label":"A.2","competences":["R","V"],"items":[{"id":"v1xk8bd9","label":"Système, référentiel, bilan des forces","points":0.5},{"id":"0n6kn2mr","label":"PFD à l'équilibre","points":0.5},{"id":"vvjmns3d","label":"Expression","points":0.5},{"id":"ard8clho","label":"Homogénéité vérifiée","points":0.5},{"id":"ws8thypy","label":"Pertinence physique","points":1}]},{"id":"65g5k5eb","label":"A.3","competences":["N"],"items":[{"id":"hhe8cy5u","label":"Expression de x'","points":0.5},{"id":"3rswo2tn","label":"x-x'","points":0.5}]},{"id":"4daat3ry","label":"A.4","competences":["N","V"],"items":[{"id":"s9n5gph0","label":"OdG de l'élongation et de M corrects","points":0.5},{"id":"e6x1kdqh","label":"Calcul correct","points":0.5}]},{"id":"yf4kqzht","label":"A.5","competences":["R"],"items":[{"id":"p66dcxec","label":"PFD établi correctement (BdF...)","points":1},{"id":"uk5a5ojh","label":"a0 et b0","points":2}]},{"id":"12g1ka58","label":"B.1","competences":["N"],"items":[{"id":"hsquwpmj","label":"F0 (justifié)","points":0.5},{"id":"ib2gyv7z","label":"F1 (justifié)","points":0.5},{"id":"9dj4q8g0","label":"omega (justifié)","points":0.5}]},{"id":"nktks2dc","label":"B.2","competences":["A"],"items":[{"id":"imxscsat","label":"pulsation propre","points":0.5},{"id":"vz3zt0rg","label":"facteur de qualité","points":0.5},{"id":"w4hfyxq0","label":"signification omega0","points":1},{"id":"x625t430","label":"signification Q","points":1}]},{"id":"mpxhwmog","label":"B.3","competences":["R"],"items":[{"id":"4typ04yi","label":"Etablir la solution complexe","points":1},{"id":"m0105u6a","label":"Passage au module","points":1}]},{"id":"2bo8lpvg","label":"B.4","competences":["R"],"items":[{"id":"rbfwfsdw","label":"Dérivation OK","points":1}]},{"id":"l0tcopja","label":"B.5","competences":["R","N"],"items":[{"id":"ys0ur3tq","label":"Comportements asymptotiques","points":0.5},{"id":"lq3lcyvh","label":"Omega0 et sa valeur numérique","points":1},{"id":"yg72hkp3","label":"P_L max","points":0.5},{"id":"hmn1n910","label":"Allure","points":0.5},{"id":"mei09vko","label":"Légende et axes","points":0.5}]}]}],"nomDS":"DS 05","dateDS":"14 février 2026"},{"id":"1mfgyyzi","name":"DS 06","exercises":[{"id":"rjox38yy","title":"Exercice 1","questions":[{"id":"tlq6oq4p","label":"1","competences":["R"],"items":[{"id":"9m22h4n6","label":"Item 1","points":1}]}]}]}],"students":[{"id":"yo8bz0w6","nom":"Collet","prenom":"Tristan"},{"id":"irk7ejyf","nom":"Alliot","prenom":"Ewann"},{"id":"7z1c6b0p","nom":"David","prenom":"Ruben"},{"id":"pwjrbcey","nom":"Amant","prenom":"Félix"},{"id":"dvaud5yg","nom":"Sadeki","prenom":"Heni"},{"id":"7bilm4tk","nom":"Oberlin","prenom":"Nathan"},{"id":"tbfvcttu","nom":"Lefèvre","prenom":"Maximilien"},{"id":"7fk7lv49","nom":"Delort","prenom":"Louis"},{"id":"cow5mnbu","nom":"El Annaz","prenom":"Anis"},{"id":"ut7vpvl7","nom":"Salatti","prenom":"Timéo"},{"id":"qyk9hnyq","nom":"Lepéculier","prenom":"César"},{"id":"4wz55f5x","nom":"Cerles","prenom":"Pablo"},{"id":"ibyliehb","nom":"Cheung","prenom":"Chris"},{"id":"iv3pn9eh","nom":"Martin","prenom":"Lucas"},{"id":"gnrt0035","nom":"Caplong","prenom":"Mathis"},{"id":"fckepo2k","nom":"Duffault","prenom":"Oscar"},{"id":"h6u0fhb4","nom":"Singbo","prenom":"Yanis"},{"id":"50u2ckr0","nom":"Gimeno Limoni","prenom":"Tristan"},{"id":"lbo37lc6","nom":"Laurent","prenom":"Clarence"},{"id":"ra1eyd6b","nom":"Lahmani","prenom":"Bilal"},{"id":"4pdli4fx","nom":"Mehring","prenom":"Lirio"},{"id":"ee6snp15","nom":"Nebot","prenom":"Nathan"},{"id":"76kf3ans","nom":"Muhammad","prenom":"Daniel"},{"id":"0aep7o37","nom":"Malet","prenom":"Raphaël"},{"id":"h42l60z5","nom":"Bance","prenom":"Arthur"},{"id":"c678r4v3","nom":"Rougelot","prenom":"Rémi"},{"id":"vuqxmzok","nom":"Capallere","prenom":"Maxence"},{"id":"w0yh056n","nom":"De Vos","prenom":"Wilhelm"},{"id":"stino2h1","nom":"Egea","prenom":"Mathieu"},{"id":"a6ktjg7r","nom":"Boukerroucha","prenom":"Ihab Ali"},{"id":"d8tahscw","nom":"Bendifallah","prenom":"Rayan"},{"id":"35x9q3wq","nom":"Linguet","prenom":"Emmanuel"},{"id":"pct0o65u","nom":"Aleksanyan","prenom":"Meri"},{"id":"vx303o2a","nom":"Pouget","prenom":"Antoine"},{"id":"iotp3mj2","nom":"Crisnaire","prenom":"Maxime"},{"id":"ecoku53v","nom":"Bompard","prenom":"Nina"},{"id":"55qn9jmx","nom":"Coralli","prenom":"Raphaël"},{"id":"0mqpz6ho","nom":"Julia","prenom":"Loris"},{"id":"7r4x5hak","nom":"Coppi","prenom":"Luann-Nam"},{"id":"ixx95kom","nom":"Comallonga","prenom":"Eris"},{"id":"o00zbti8","nom":"Bourlier","prenom":"Jaouën"},{"id":"ipdq6d8w","nom":"Garrigues","prenom":"Téofane"},{"id":"ttd3yvfv","nom":"Nguyen","prenom":"Leny"},{"id":"y95gn4y0","nom":"de Colbert","prenom":"Baptiste"}],"grades":{"ql6b5gju__507h6qdb":true,"ql6b5gju__y66u2h7e":true,"yo8bz0w6__507h6qdb":true,"yo8bz0w6__mgi5bmx2":true,"yo8bz0w6__y66u2h7e":true,"yo8bz0w6__oijcz4e8":true,"yo8bz0w6__sdyxylhq":true,"yo8bz0w6__5oczvu25":true,"yo8bz0w6__npucjsxi":true,"yo8bz0w6__w6to2wwr":true,"yo8bz0w6__1b57sf5o":true,"yo8bz0w6__5jixnhaz":true,"yo8bz0w6__24qbxv18":true,"yo8bz0w6__crik6b73":true,"yo8bz0w6__4owexrnb":true,"yo8bz0w6__9hausbej":true,"yo8bz0w6__64yvr5uh":true,"yo8bz0w6__0h44m53n":true,"yo8bz0w6__a1t5kvrl":true,"yo8bz0w6__afwmc9g5":true,"yo8bz0w6__8c6yq3kg":true,"yo8bz0w6__898c7d5x":true,"yo8bz0w6__ejkd89o8":true,"yo8bz0w6__ju3qxgji":true,"yo8bz0w6__14gu1btu":true,"yo8bz0w6__k2h1nkw9":true,"yo8bz0w6__ed8ag4zc":true,"yo8bz0w6__c1gvhv4o":true,"yo8bz0w6__d8siusny":true,"yo8bz0w6__xg8nykmv":true,"yo8bz0w6__3klmivf1":true,"yo8bz0w6__pq8drcrt":true,"yo8bz0w6__8wqogyuv":true,"yo8bz0w6__3u2k3d8x":true,"yo8bz0w6__9wrqnjc0":true,"yo8bz0w6__dkneh8h5":true,"yo8bz0w6__c4357fs1":true,"yo8bz0w6__pjcwjaq6":true,"yo8bz0w6__7juj0kaq":true,"yo8bz0w6__v1xk8bd9":true,"yo8bz0w6__0n6kn2mr":true,"yo8bz0w6__vvjmns3d":true,"yo8bz0w6__ard8clho":true,"yo8bz0w6__ws8thypy":true,"yo8bz0w6__hhe8cy5u":true,"yo8bz0w6__3rswo2tn":true,"yo8bz0w6__s9n5gph0":true,"yo8bz0w6__p66dcxec":true,"yo8bz0w6__hsquwpmj":true,"yo8bz0w6__ib2gyv7z":true,"yo8bz0w6__imxscsat":true,"yo8bz0w6__vz3zt0rg":true,"irk7ejyf__sdyxylhq":true,"irk7ejyf__5jixnhaz":true,"irk7ejyf__crik6b73":true,"irk7ejyf__4owexrnb":true,"irk7ejyf__9hausbej":true,"irk7ejyf__64yvr5uh":true,"irk7ejyf__0h44m53n":true,"irk7ejyf__a1t5kvrl":true,"irk7ejyf__8c6yq3kg":true,"irk7ejyf__afwmc9g5":true,"irk7ejyf__898c7d5x":true,"irk7ejyf__ejkd89o8":true,"irk7ejyf__fhhx1cha":true,"irk7ejyf__7hcfqp9x":false,"irk7ejyf__ju3qxgji":true,"irk7ejyf__14gu1btu":true,"irk7ejyf__k2h1nkw9":true,"irk7ejyf__d8siusny":true,"irk7ejyf__8fkni8cd":true,"irk7ejyf__pq8drcrt":true,"irk7ejyf__8wqogyuv":true,"irk7ejyf__9wrqnjc0":false,"irk7ejyf__zfinlior":false,"irk7ejyf__c4357fs1":true,"irk7ejyf__7juj0kaq":true,"irk7ejyf__v1xk8bd9":false,"irk7ejyf__0n6kn2mr":true,"irk7ejyf__ws8thypy":true,"irk7ejyf__3rswo2tn":true,"irk7ejyf__s9n5gph0":true,"irk7ejyf__e6x1kdqh":true,"irk7ejyf__hsquwpmj":true,"irk7ejyf__ib2gyv7z":true,"irk7ejyf__9dj4q8g0":true,"irk7ejyf__imxscsat":true,"irk7ejyf__vz3zt0rg":true,"irk7ejyf__w4hfyxq0":true,"irk7ejyf__4typ04yi":true,"irk7ejyf__m0105u6a":true,"irk7ejyf__rbfwfsdw":true,"treated_yo8bz0w6_9hn1vj87":true,"treated_yo8bz0w6_06nuka5q":true,"treated_yo8bz0w6_yf6n8api":true,"treated_yo8bz0w6_mpxhwmog":true,"treated_irk7ejyf_55yukdid":true,"treated_irk7ejyf_9hn1vj87":true,"treated_irk7ejyf_06nuka5q":true,"treated_irk7ejyf_0m5yzvkt":true,"treated_irk7ejyf_32pzdqqp":true,"treated_irk7ejyf_sr75c1mm":true,"treated_irk7ejyf_yf6n8api":true,"treated_irk7ejyf_yf4kqzht":true,"7z1c6b0p__507h6qdb":true,"7z1c6b0p__lzhrlfua":true,"7z1c6b0p__wqz4usbe":true,"7z1c6b0p__47ljzdg8":true,"7z1c6b0p__oijcz4e8":true,"7z1c6b0p__sdyxylhq":true,"7z1c6b0p__0eegwxql":true,"7z1c6b0p__npucjsxi":true,"7z1c6b0p__w6to2wwr":true,"7z1c6b0p__5jixnhaz":true,"7z1c6b0p__crik6b73":true,"7z1c6b0p__4owexrnb":true,"7z1c6b0p__9hausbej":true,"7z1c6b0p__64yvr5uh":true,"7z1c6b0p__0h44m53n":true,"7z1c6b0p__a1t5kvrl":true,"7z1c6b0p__afwmc9g5":true,"7z1c6b0p__8c6yq3kg":true,"7z1c6b0p__898c7d5x":true,"7z1c6b0p__ejkd89o8":true,"7z1c6b0p__fhhx1cha":true,"7z1c6b0p__7hcfqp9x":true,"7z1c6b0p__ju3qxgji":true,"7z1c6b0p__14gu1btu":true,"7z1c6b0p__k2h1nkw9":true,"7z1c6b0p__ed8ag4zc":true,"7z1c6b0p__d8siusny":true,"7z1c6b0p__8fkni8cd":true,"7z1c6b0p__7juj0kaq":true,"7z1c6b0p__v1xk8bd9":true,"7z1c6b0p__0n6kn2mr":true,"7z1c6b0p__vvjmns3d":true,"7z1c6b0p__ard8clho":true,"7z1c6b0p__ws8thypy":true,"7z1c6b0p__hhe8cy5u":true,"7z1c6b0p__3rswo2tn":true,"7z1c6b0p__s9n5gph0":true,"7z1c6b0p__e6x1kdqh":true,"7z1c6b0p__p66dcxec":true,"7z1c6b0p__uk5a5ojh":true,"7z1c6b0p__ib2gyv7z":true,"7z1c6b0p__9dj4q8g0":true,"pwjrbcey__5jixnhaz":true,"pwjrbcey__24qbxv18":true,"pwjrbcey__crik6b73":true,"pwjrbcey__4owexrnb":true,"pwjrbcey__9hausbej":true,"pwjrbcey__64yvr5uh":true,"pwjrbcey__0h44m53n":true,"pwjrbcey__a1t5kvrl":true,"pwjrbcey__afwmc9g5":true,"pwjrbcey__8c6yq3kg":true,"pwjrbcey__898c7d5x":true,"pwjrbcey__ejkd89o8":true,"pwjrbcey__fhhx1cha":true,"pwjrbcey__ju3qxgji":true,"pwjrbcey__14gu1btu":true,"pwjrbcey__k2h1nkw9":true,"treated_pwjrbcey_bux35oit":true,"pwjrbcey__pq8drcrt":true,"treated_pwjrbcey_9tafd606":true,"pwjrbcey__9wrqnjc0":true,"pwjrbcey__dkneh8h5":true,"pwjrbcey__7juj0kaq":true,"pwjrbcey__v1xk8bd9":true,"pwjrbcey__0n6kn2mr":true,"pwjrbcey__vvjmns3d":true,"pwjrbcey__ard8clho":true,"pwjrbcey__ws8thypy":true,"pwjrbcey__hhe8cy5u":true,"pwjrbcey__3rswo2tn":true,"pwjrbcey__s9n5gph0":true,"pwjrbcey__p66dcxec":true,"pwjrbcey__hsquwpmj":true,"pwjrbcey__ib2gyv7z":true,"pwjrbcey__imxscsat":true,"pwjrbcey__vz3zt0rg":true,"pwjrbcey__4typ04yi":true,"pwjrbcey__m0105u6a":true,"treated_pwjrbcey_2bo8lpvg":true,"pwjrbcey__ys0ur3tq":true,"pwjrbcey__yg72hkp3":true,"pwjrbcey__hmn1n910":true,"pwjrbcey__mei09vko":true,"pwjrbcey__507h6qdb":true,"pwjrbcey__y66u2h7e":true,"treated_pwjrbcey_9hn1vj87":true,"treated_pwjrbcey_awsnqs09":true,"pwjrbcey__sdyxylhq":true,"treated_pwjrbcey_06nuka5q":true,"pwjrbcey__5oczvu25":true,"pwjrbcey__npucjsxi":true,"treated_pwjrbcey_32pzdqqp":true,"dvaud5yg__5jixnhaz":true,"dvaud5yg__crik6b73":true,"dvaud5yg__9hausbej":true,"dvaud5yg__4owexrnb":true,"dvaud5yg__0h44m53n":true,"dvaud5yg__a1t5kvrl":true,"dvaud5yg__afwmc9g5":true,"dvaud5yg__898c7d5x":true,"dvaud5yg__ejkd89o8":true,"dvaud5yg__fhhx1cha":true,"dvaud5yg__7hcfqp9x":true,"dvaud5yg__ju3qxgji":true,"dvaud5yg__14gu1btu":true,"dvaud5yg__k2h1nkw9":true,"treated_dvaud5yg_bux35oit":true,"dvaud5yg__pq8drcrt":true,"dvaud5yg__8wqogyuv":true,"treated_dvaud5yg_9tafd606":true,"dvaud5yg__9wrqnjc0":true,"dvaud5yg__dkneh8h5":true,"dvaud5yg__7juj0kaq":true,"dvaud5yg__v1xk8bd9":true,"dvaud5yg__0n6kn2mr":true,"dvaud5yg__vvjmns3d":true,"dvaud5yg__hhe8cy5u":true,"dvaud5yg__3rswo2tn":true,"dvaud5yg__s9n5gph0":true,"dvaud5yg__p66dcxec":false,"treated_dvaud5yg_yf4kqzht":true,"dvaud5yg__hsquwpmj":true,"dvaud5yg__ib2gyv7z":true,"dvaud5yg__9dj4q8g0":true,"dvaud5yg__imxscsat":false,"dvaud5yg__w4hfyxq0":false,"dvaud5yg__vz3zt0rg":true,"treated_dvaud5yg_mpxhwmog":true,"treated_dvaud5yg_55yukdid":true,"treated_dvaud5yg_9hn1vj87":true,"dvaud5yg__sdyxylhq":true,"treated_dvaud5yg_06nuka5q":true,"dvaud5yg__5oczvu25":false,"treated_dvaud5yg_0m5yzvkt":true,"treated_dvaud5yg_32pzdqqp":true,"7bilm4tk__507h6qdb":true,"7bilm4tk__y66u2h7e":true,"7bilm4tk__oijcz4e8":true,"7bilm4tk__sdyxylhq":true,"7bilm4tk__5jixnhaz":true,"7bilm4tk__24qbxv18":true,"7bilm4tk__crik6b73":true,"7bilm4tk__4owexrnb":true,"7bilm4tk__9hausbej":true,"7bilm4tk__64yvr5uh":true,"7bilm4tk__0h44m53n":true,"7bilm4tk__a1t5kvrl":true,"7bilm4tk__afwmc9g5":true,"7bilm4tk__8c6yq3kg":true,"7bilm4tk__898c7d5x":true,"7bilm4tk__ejkd89o8":true,"7bilm4tk__fhhx1cha":true,"7bilm4tk__ju3qxgji":true,"7bilm4tk__14gu1btu":true,"7bilm4tk__k2h1nkw9":true,"7bilm4tk__7juj0kaq":true,"7bilm4tk__v1xk8bd9":true,"7bilm4tk__0n6kn2mr":true,"7bilm4tk__vvjmns3d":true,"7bilm4tk__ard8clho":true,"7bilm4tk__ws8thypy":true,"7bilm4tk__hhe8cy5u":true,"7bilm4tk__3rswo2tn":true,"7bilm4tk__s9n5gph0":true,"7bilm4tk__e6x1kdqh":true,"7bilm4tk__p66dcxec":true,"7bilm4tk__hsquwpmj":true,"7bilm4tk__ib2gyv7z":true,"tbfvcttu__5jixnhaz":true,"tbfvcttu__24qbxv18":true,"tbfvcttu__crik6b73":true,"tbfvcttu__4owexrnb":true,"tbfvcttu__64yvr5uh":true,"tbfvcttu__0h44m53n":true,"tbfvcttu__a1t5kvrl":true,"tbfvcttu__898c7d5x":true,"tbfvcttu__ejkd89o8":true,"tbfvcttu__afwmc9g5":true,"tbfvcttu__fhhx1cha":true,"tbfvcttu__7hcfqp9x":true,"tbfvcttu__14gu1btu":true,"tbfvcttu__k2h1nkw9":true,"treated_tbfvcttu_bux35oit":true,"tbfvcttu__507h6qdb":true,"tbfvcttu__y66u2h7e":true,"tbfvcttu__sdyxylhq":true,"tbfvcttu__5oczvu25":true,"tbfvcttu__npucjsxi":true,"treated_tbfvcttu_32pzdqqp":true,"tbfvcttu__7juj0kaq":true,"7fk7lv49__507h6qdb":true,"7fk7lv49__y66u2h7e":true,"treated_7fk7lv49_9hn1vj87":true,"7fk7lv49__oijcz4e8":true,"7fk7lv49__sdyxylhq":true,"treated_7fk7lv49_06nuka5q":true,"7fk7lv49__5oczvu25":true,"7fk7lv49__npucjsxi":true,"treated_7fk7lv49_32pzdqqp":true,"7fk7lv49__5jixnhaz":true,"7fk7lv49__crik6b73":true,"7fk7lv49__4owexrnb":true,"7fk7lv49__9hausbej":true,"7fk7lv49__64yvr5uh":true,"7fk7lv49__0h44m53n":true,"7fk7lv49__a1t5kvrl":true,"7fk7lv49__afwmc9g5":true,"7fk7lv49__898c7d5x":true,"7fk7lv49__ejkd89o8":true,"7fk7lv49__fhhx1cha":true,"7fk7lv49__7hcfqp9x":true,"7fk7lv49__14gu1btu":true,"7fk7lv49__k2h1nkw9":true,"treated_7fk7lv49_bux35oit":true,"7fk7lv49__pq8drcrt":true,"7fk7lv49__8wqogyuv":true,"7fk7lv49__3u2k3d8x":true,"7fk7lv49__9wrqnjc0":true,"7fk7lv49__dkneh8h5":true,"7fk7lv49__zfinlior":true,"treated_7fk7lv49_ok2syrrk":true,"7fk7lv49__7juj0kaq":true,"7fk7lv49__v1xk8bd9":true,"7fk7lv49__0n6kn2mr":true,"7fk7lv49__vvjmns3d":true,"7fk7lv49__ard8clho":true,"7fk7lv49__hhe8cy5u":true,"7fk7lv49__3rswo2tn":true,"7fk7lv49__s9n5gph0":true,"7fk7lv49__e6x1kdqh":true,"7fk7lv49__hsquwpmj":true,"7fk7lv49__ib2gyv7z":true,"7fk7lv49__9dj4q8g0":true,"7fk7lv49__imxscsat":true,"7fk7lv49__vz3zt0rg":true,"cow5mnbu__5jixnhaz":true,"cow5mnbu__24qbxv18":true,"cow5mnbu__4owexrnb":true,"cow5mnbu__crik6b73":true,"cow5mnbu__64yvr5uh":true,"cow5mnbu__0h44m53n":true,"cow5mnbu__a1t5kvrl":true,"cow5mnbu__afwmc9g5":true,"cow5mnbu__8c6yq3kg":true,"cow5mnbu__898c7d5x":true,"cow5mnbu__ejkd89o8":true,"treated_cow5mnbu_2n64gszw":true,"cow5mnbu__14gu1btu":true,"cow5mnbu__k2h1nkw9":true,"cow5mnbu__ed8ag4zc":true,"cow5mnbu__d8siusny":true,"cow5mnbu__8fkni8cd":true,"cow5mnbu__pq8drcrt":true,"cow5mnbu__8wqogyuv":true,"cow5mnbu__xg8nykmv":true,"cow5mnbu__3klmivf1":true,"cow5mnbu__7juj0kaq":true,"cow5mnbu__v1xk8bd9":true,"cow5mnbu__0n6kn2mr":true,"cow5mnbu__vvjmns3d":true,"cow5mnbu__ws8thypy":true,"cow5mnbu__hhe8cy5u":true,"cow5mnbu__3rswo2tn":true,"cow5mnbu__s9n5gph0":true,"cow5mnbu__p66dcxec":true,"cow5mnbu__uk5a5ojh":true,"cow5mnbu__hsquwpmj":true,"cow5mnbu__ib2gyv7z":true,"cow5mnbu__9dj4q8g0":true,"cow5mnbu__imxscsat":true,"cow5mnbu__vz3zt0rg":true,"cow5mnbu__w4hfyxq0":true,"cow5mnbu__x625t430":true,"treated_cow5mnbu_mpxhwmog":true,"cow5mnbu__rbfwfsdw":true,"treated_cow5mnbu_l0tcopja":true,"cow5mnbu__ys0ur3tq":true,"cow5mnbu__507h6qdb":true,"cow5mnbu__y66u2h7e":true,"treated_cow5mnbu_9hn1vj87":true,"ut7vpvl7__47ljzdg8":false,"ut7vpvl7__wqz4usbe":false,"ut7vpvl7__lzhrlfua":false,"treated_ut7vpvl7_awsnqs09":true,"ut7vpvl7__5oczvu25":true,"ut7vpvl7__5jixnhaz":true,"ut7vpvl7__crik6b73":true,"ut7vpvl7__4owexrnb":false,"ut7vpvl7__9hausbej":true,"ut7vpvl7__64yvr5uh":true,"ut7vpvl7__0h44m53n":true,"ut7vpvl7__a1t5kvrl":true,"ut7vpvl7__afwmc9g5":true,"ut7vpvl7__898c7d5x":true,"ut7vpvl7__ju3qxgji":true,"ut7vpvl7__7hcfqp9x":true,"ut7vpvl7__fhhx1cha":true,"ut7vpvl7__14gu1btu":true,"ut7vpvl7__k2h1nkw9":true,"ut7vpvl7__pq8drcrt":true,"ut7vpvl7__3u2k3d8x":false,"treated_ut7vpvl7_9tafd606":true,"treated_ut7vpvl7_sr75c1mm":true,"ut7vpvl7__zfinlior":true,"treated_ut7vpvl7_trysfn1h":true,"treated_ut7vpvl7_ok2syrrk":true,"treated_ut7vpvl7_4hxyhek9":true,"ut7vpvl7__7juj0kaq":true,"ut7vpvl7__v1xk8bd9":true,"ut7vpvl7__0n6kn2mr":true,"ut7vpvl7__vvjmns3d":true,"ut7vpvl7__ard8clho":true,"ut7vpvl7__ws8thypy":true,"ut7vpvl7__hhe8cy5u":true,"ut7vpvl7__3rswo2tn":true,"ut7vpvl7__s9n5gph0":true,"ut7vpvl7__e6x1kdqh":true,"ut7vpvl7__p66dcxec":true,"ut7vpvl7__uk5a5ojh":true,"ut7vpvl7__9dj4q8g0":true,"ut7vpvl7__imxscsat":true,"treated_ut7vpvl7_mpxhwmog":true,"qyk9hnyq__5jixnhaz":true,"qyk9hnyq__24qbxv18":true,"qyk9hnyq__crik6b73":true,"qyk9hnyq__4owexrnb":true,"qyk9hnyq__9hausbej":true,"qyk9hnyq__64yvr5uh":true,"qyk9hnyq__0h44m53n":true,"qyk9hnyq__a1t5kvrl":true,"qyk9hnyq__afwmc9g5":true,"qyk9hnyq__8c6yq3kg":true,"qyk9hnyq__898c7d5x":true,"qyk9hnyq__ejkd89o8":true,"qyk9hnyq__fhhx1cha":true,"qyk9hnyq__7hcfqp9x":true,"qyk9hnyq__ju3qxgji":true,"qyk9hnyq__14gu1btu":true,"qyk9hnyq__k2h1nkw9":true,"qyk9hnyq__ed8ag4zc":true,"treated_qyk9hnyq_bux35oit":true,"qyk9hnyq__9wrqnjc0":true,"qyk9hnyq__dkneh8h5":true,"qyk9hnyq__zfinlior":true,"qyk9hnyq__507h6qdb":true,"qyk9hnyq__y66u2h7e":true,"qyk9hnyq__lzhrlfua":true,"qyk9hnyq__oijcz4e8":true,"treated_qyk9hnyq_06nuka5q":true,"qyk9hnyq__5oczvu25":true,"qyk9hnyq__npucjsxi":true,"treated_qyk9hnyq_32pzdqqp":true,"qyk9hnyq__7juj0kaq":true,"qyk9hnyq__0n6kn2mr":true,"qyk9hnyq__vvjmns3d":true,"qyk9hnyq__ard8clho":true,"qyk9hnyq__ws8thypy":true,"qyk9hnyq__hhe8cy5u":true,"qyk9hnyq__3rswo2tn":true,"qyk9hnyq__s9n5gph0":true,"qyk9hnyq__e6x1kdqh":true,"qyk9hnyq__p66dcxec":true,"qyk9hnyq__9dj4q8g0":true,"qyk9hnyq__imxscsat":true,"qyk9hnyq__vz3zt0rg":true,"4wz55f5x__24qbxv18":true,"4wz55f5x__crik6b73":true,"4wz55f5x__4owexrnb":true,"4wz55f5x__9hausbej":true,"4wz55f5x__64yvr5uh":true,"4wz55f5x__0h44m53n":true,"4wz55f5x__a1t5kvrl":true,"4wz55f5x__afwmc9g5":true,"4wz55f5x__898c7d5x":true,"4wz55f5x__ejkd89o8":true,"4wz55f5x__fhhx1cha":true,"4wz55f5x__7hcfqp9x":true,"4wz55f5x__ju3qxgji":true,"4wz55f5x__k2h1nkw9":true,"4wz55f5x__ed8ag4zc":true,"4wz55f5x__9wrqnjc0":true,"4wz55f5x__dkneh8h5":true,"treated_4wz55f5x_yf6n8api":true,"treated_4wz55f5x_55yukdid":true,"4wz55f5x__sdyxylhq":true,"treated_4wz55f5x_06nuka5q":true,"4wz55f5x__5oczvu25":true,"treated_4wz55f5x_32pzdqqp":true,"treated_4wz55f5x_drgof1xu":true,"4wz55f5x__v1xk8bd9":true,"4wz55f5x__0n6kn2mr":true,"4wz55f5x__vvjmns3d":true,"4wz55f5x__ws8thypy":true,"4wz55f5x__hhe8cy5u":true,"4wz55f5x__3rswo2tn":true,"4wz55f5x__s9n5gph0":true,"4wz55f5x__p66dcxec":true,"4wz55f5x__uk5a5ojh":true,"treated_4wz55f5x_nktks2dc":true,"treated_4wz55f5x_mpxhwmog":true,"ibyliehb__507h6qdb":true,"ibyliehb__y66u2h7e":true,"treated_ibyliehb_9hn1vj87":true,"ibyliehb__sdyxylhq":true,"treated_ibyliehb_06nuka5q":true,"treated_ibyliehb_0m5yzvkt":true,"treated_ibyliehb_32pzdqqp":true,"ibyliehb__24qbxv18":true,"ibyliehb__crik6b73":true,"ibyliehb__4owexrnb":true,"ibyliehb__9hausbej":true,"ibyliehb__0h44m53n":true,"ibyliehb__a1t5kvrl":true,"ibyliehb__afwmc9g5":true,"ibyliehb__898c7d5x":true,"ibyliehb__fhhx1cha":true,"ibyliehb__7hcfqp9x":true,"ibyliehb__14gu1btu":true,"ibyliehb__9wrqnjc0":true,"ibyliehb__dkneh8h5":true,"ibyliehb__zfinlior":true,"treated_ibyliehb_trysfn1h":true,"treated_ibyliehb_drgof1xu":true,"treated_ibyliehb_lxg44keb":true,"treated_ibyliehb_yf4kqzht":true,"ibyliehb__hsquwpmj":true,"ibyliehb__ib2gyv7z":true,"iv3pn9eh__5jixnhaz":true,"iv3pn9eh__crik6b73":true,"iv3pn9eh__4owexrnb":true,"iv3pn9eh__64yvr5uh":true,"iv3pn9eh__0h44m53n":true,"iv3pn9eh__a1t5kvrl":true,"iv3pn9eh__afwmc9g5":true,"iv3pn9eh__fhhx1cha":true,"iv3pn9eh__14gu1btu":true,"iv3pn9eh__k2h1nkw9":true,"iv3pn9eh__9wrqnjc0":true,"iv3pn9eh__dkneh8h5":true,"iv3pn9eh__507h6qdb":true,"iv3pn9eh__y66u2h7e":false,"iv3pn9eh__oijcz4e8":true,"iv3pn9eh__sdyxylhq":true,"treated_iv3pn9eh_06nuka5q":true,"iv3pn9eh__5oczvu25":true,"treated_iv3pn9eh_32pzdqqp":true,"treated_iv3pn9eh_drgof1xu":true,"iv3pn9eh__v1xk8bd9":true,"iv3pn9eh__0n6kn2mr":true,"iv3pn9eh__vvjmns3d":true,"iv3pn9eh__hhe8cy5u":true,"iv3pn9eh__3rswo2tn":true,"iv3pn9eh__s9n5gph0":true,"iv3pn9eh__p66dcxec":true,"iv3pn9eh__hsquwpmj":true,"iv3pn9eh__9dj4q8g0":true,"iv3pn9eh__imxscsat":true,"iv3pn9eh__vz3zt0rg":true,"treated_gnrt0035_55yukdid":true,"treated_gnrt0035_9hn1vj87":true,"gnrt0035__oijcz4e8":true,"treated_gnrt0035_06nuka5q":true,"treated_gnrt0035_0m5yzvkt":true,"gnrt0035__w6to2wwr":true,"gnrt0035__1b57sf5o":true,"treated_gnrt0035_y3sg56lx":true,"gnrt0035__crik6b73":true,"gnrt0035__0h44m53n":true,"gnrt0035__a1t5kvrl":true,"gnrt0035__afwmc9g5":true,"gnrt0035__7hcfqp9x":true,"gnrt0035__ju3qxgji":true,"treated_gnrt0035_ypsev6fy":true,"treated_gnrt0035_bux35oit":true,"treated_gnrt0035_rokk8ye2":true,"treated_gnrt0035_9tafd606":true,"gnrt0035__9wrqnjc0":true,"gnrt0035__dkneh8h5":true,"gnrt0035__7juj0kaq":true,"gnrt0035__v1xk8bd9":true,"gnrt0035__0n6kn2mr":true,"gnrt0035__vvjmns3d":true,"gnrt0035__ws8thypy":true,"gnrt0035__hhe8cy5u":true,"gnrt0035__3rswo2tn":true,"treated_fckepo2k_55yukdid":true,"fckepo2k__lzhrlfua":true,"fckepo2k__oijcz4e8":true,"fckepo2k__sdyxylhq":true,"treated_fckepo2k_06nuka5q":true,"fckepo2k__5oczvu25":true,"fckepo2k__npucjsxi":true,"fckepo2k__w6to2wwr":true,"fckepo2k__5jixnhaz":true,"fckepo2k__24qbxv18":true,"fckepo2k__crik6b73":true,"fckepo2k__4owexrnb":true,"fckepo2k__9hausbej":true,"fckepo2k__64yvr5uh":true,"fckepo2k__0h44m53n":true,"fckepo2k__a1t5kvrl":true,"fckepo2k__afwmc9g5":true,"fckepo2k__8c6yq3kg":true,"fckepo2k__898c7d5x":true,"fckepo2k__ejkd89o8":true,"fckepo2k__fhhx1cha":true,"fckepo2k__7hcfqp9x":true,"fckepo2k__ju3qxgji":true,"fckepo2k__14gu1btu":true,"fckepo2k__k2h1nkw9":true,"treated_fckepo2k_bux35oit":true,"fckepo2k__pq8drcrt":true,"fckepo2k__8wqogyuv":true,"fckepo2k__3u2k3d8x":true,"fckepo2k__9wrqnjc0":true,"fckepo2k__dkneh8h5":true,"fckepo2k__7juj0kaq":true,"fckepo2k__v1xk8bd9":true,"fckepo2k__0n6kn2mr":true,"fckepo2k__vvjmns3d":true,"fckepo2k__ard8clho":true,"fckepo2k__ws8thypy":true,"treated_fckepo2k_65g5k5eb":true,"fckepo2k__s9n5gph0":true,"fckepo2k__e6x1kdqh":true,"h6u0fhb4__507h6qdb":true,"h6u0fhb4__y66u2h7e":true,"h6u0fhb4__sdyxylhq":true,"h6u0fhb4__5oczvu25":true,"h6u0fhb4__npucjsxi":true,"h6u0fhb4__w6to2wwr":true,"h6u0fhb4__1b57sf5o":true,"h6u0fhb4__5jixnhaz":true,"h6u0fhb4__24qbxv18":true,"h6u0fhb4__crik6b73":true,"h6u0fhb4__4owexrnb":true,"h6u0fhb4__9hausbej":true,"h6u0fhb4__64yvr5uh":true,"h6u0fhb4__0h44m53n":true,"h6u0fhb4__a1t5kvrl":true,"h6u0fhb4__afwmc9g5":true,"h6u0fhb4__8c6yq3kg":true,"h6u0fhb4__898c7d5x":true,"h6u0fhb4__ejkd89o8":true,"h6u0fhb4__fhhx1cha":true,"h6u0fhb4__7hcfqp9x":true,"h6u0fhb4__ju3qxgji":true,"h6u0fhb4__14gu1btu":true,"h6u0fhb4__k2h1nkw9":true,"h6u0fhb4__ed8ag4zc":true,"h6u0fhb4__c1gvhv4o":true,"h6u0fhb4__d8siusny":true,"h6u0fhb4__8fkni8cd":true,"h6u0fhb4__xg8nykmv":true,"h6u0fhb4__3klmivf1":true,"50u2ckr0__5jixnhaz":true,"50u2ckr0__crik6b73":true,"50u2ckr0__4owexrnb":true,"50u2ckr0__9hausbej":true,"50u2ckr0__64yvr5uh":true,"50u2ckr0__afwmc9g5":true,"50u2ckr0__fhhx1cha":true,"50u2ckr0__7hcfqp9x":true,"50u2ckr0__ju3qxgji":true,"50u2ckr0__14gu1btu":true,"50u2ckr0__k2h1nkw9":true,"50u2ckr0__9wrqnjc0":true,"50u2ckr0__dkneh8h5":true,"50u2ckr0__zfinlior":true,"50u2ckr0__507h6qdb":true,"50u2ckr0__y66u2h7e":true,"50u2ckr0__oijcz4e8":true,"50u2ckr0__sdyxylhq":true,"50u2ckr0__0eegwxql":true,"50u2ckr0__5oczvu25":true,"50u2ckr0__npucjsxi":true,"50u2ckr0__w6to2wwr":true,"50u2ckr0__7juj0kaq":true,"50u2ckr0__v1xk8bd9":true,"50u2ckr0__0n6kn2mr":true,"50u2ckr0__vvjmns3d":true,"50u2ckr0__ard8clho":true,"50u2ckr0__ws8thypy":true,"50u2ckr0__hhe8cy5u":true,"50u2ckr0__3rswo2tn":true,"50u2ckr0__s9n5gph0":true,"50u2ckr0__e6x1kdqh":true,"50u2ckr0__p66dcxec":true,"50u2ckr0__uk5a5ojh":true,"50u2ckr0__hsquwpmj":true,"50u2ckr0__9dj4q8g0":true,"50u2ckr0__imxscsat":true,"50u2ckr0__vz3zt0rg":true,"50u2ckr0__w4hfyxq0":true,"50u2ckr0__x625t430":true,"treated_50u2ckr0_mpxhwmog":true,"lbo37lc6__507h6qdb":true,"lbo37lc6__y66u2h7e":true,"lbo37lc6__lzhrlfua":true,"lbo37lc6__sdyxylhq":true,"lbo37lc6__0eegwxql":true,"lbo37lc6__5oczvu25":true,"lbo37lc6__npucjsxi":true,"lbo37lc6__w6to2wwr":true,"lbo37lc6__1b57sf5o":true,"lbo37lc6__5jixnhaz":true,"lbo37lc6__4owexrnb":true,"lbo37lc6__64yvr5uh":true,"lbo37lc6__0h44m53n":true,"lbo37lc6__9hausbej":true,"lbo37lc6__afwmc9g5":true,"lbo37lc6__8c6yq3kg":true,"lbo37lc6__ejkd89o8":true,"lbo37lc6__898c7d5x":true,"lbo37lc6__fhhx1cha":true,"lbo37lc6__7hcfqp9x":true,"treated_lbo37lc6_ypsev6fy":true,"lbo37lc6__k2h1nkw9":true,"lbo37lc6__9wrqnjc0":true,"lbo37lc6__dkneh8h5":true,"lbo37lc6__zfinlior":true,"lbo37lc6__7juj0kaq":true,"lbo37lc6__0n6kn2mr":true,"lbo37lc6__vvjmns3d":true,"lbo37lc6__ard8clho":true,"lbo37lc6__hhe8cy5u":true,"lbo37lc6__3rswo2tn":true,"lbo37lc6__s9n5gph0":true,"lbo37lc6__e6x1kdqh":true,"lbo37lc6__p66dcxec":true,"lbo37lc6__uk5a5ojh":true,"lbo37lc6__hsquwpmj":true,"lbo37lc6__9dj4q8g0":true,"lbo37lc6__imxscsat":true,"lbo37lc6__vz3zt0rg":true,"lbo37lc6__4typ04yi":true,"lbo37lc6__m0105u6a":true,"ra1eyd6b__5jixnhaz":true,"ra1eyd6b__crik6b73":true,"ra1eyd6b__4owexrnb":true,"ra1eyd6b__9hausbej":true,"ra1eyd6b__0h44m53n":true,"ra1eyd6b__a1t5kvrl":true,"ra1eyd6b__afwmc9g5":true,"ra1eyd6b__898c7d5x":true,"ra1eyd6b__ejkd89o8":true,"ra1eyd6b__fhhx1cha":true,"ra1eyd6b__7hcfqp9x":true,"ra1eyd6b__ju3qxgji":true,"ra1eyd6b__14gu1btu":true,"ra1eyd6b__9wrqnjc0":true,"ra1eyd6b__dkneh8h5":true,"ra1eyd6b__zfinlior":true,"ra1eyd6b__c4357fs1":true,"ra1eyd6b__5w280aq9":true,"ra1eyd6b__53xrkw14":true,"ra1eyd6b__7juj0kaq":true,"ra1eyd6b__v1xk8bd9":true,"ra1eyd6b__0n6kn2mr":true,"ra1eyd6b__ard8clho":true,"4pdli4fx__507h6qdb":true,"4pdli4fx__y66u2h7e":true,"treated_4pdli4fx_9hn1vj87":true,"4pdli4fx__oijcz4e8":true,"4pdli4fx__sdyxylhq":true,"treated_4pdli4fx_06nuka5q":true,"4pdli4fx__5oczvu25":true,"4pdli4fx__npucjsxi":true,"4pdli4fx__w6to2wwr":true,"4pdli4fx__1b57sf5o":true,"4pdli4fx__5jixnhaz":true,"4pdli4fx__24qbxv18":true,"4pdli4fx__crik6b73":true,"4pdli4fx__4owexrnb":true,"4pdli4fx__9hausbej":true,"4pdli4fx__0h44m53n":true,"4pdli4fx__a1t5kvrl":true,"4pdli4fx__898c7d5x":true,"4pdli4fx__ejkd89o8":true,"4pdli4fx__fhhx1cha":true,"4pdli4fx__7hcfqp9x":true,"4pdli4fx__14gu1btu":true,"4pdli4fx__k2h1nkw9":true,"4pdli4fx__pq8drcrt":true,"4pdli4fx__8wqogyuv":true,"treated_4pdli4fx_9tafd606":true,"4pdli4fx__9wrqnjc0":true,"4pdli4fx__dkneh8h5":true,"4pdli4fx__zfinlior":true,"treated_4pdli4fx_ok2syrrk":true,"4pdli4fx__7juj0kaq":true,"4pdli4fx__v1xk8bd9":true,"4pdli4fx__0n6kn2mr":true,"4pdli4fx__vvjmns3d":true,"4pdli4fx__ard8clho":true,"4pdli4fx__hhe8cy5u":true,"4pdli4fx__3rswo2tn":true,"4pdli4fx__s9n5gph0":true,"4pdli4fx__e6x1kdqh":true,"treated_4pdli4fx_yf4kqzht":true,"ee6snp15__507h6qdb":true,"ee6snp15__y66u2h7e":true,"ee6snp15__oijcz4e8":true,"ee6snp15__sdyxylhq":true,"ee6snp15__5oczvu25":false,"treated_ee6snp15_32pzdqqp":true,"treated_ee6snp15_0m5yzvkt":true,"ee6snp15__24qbxv18":true,"ee6snp15__crik6b73":true,"ee6snp15__4owexrnb":true,"ee6snp15__9hausbej":true,"ee6snp15__0h44m53n":false,"ee6snp15__a1t5kvrl":true,"treated_ee6snp15_2n64gszw":true,"ee6snp15__14gu1btu":true,"ee6snp15__k2h1nkw9":true,"ee6snp15__7juj0kaq":true,"ee6snp15__v1xk8bd9":true,"ee6snp15__0n6kn2mr":true,"ee6snp15__vvjmns3d":true,"ee6snp15__hhe8cy5u":true,"ee6snp15__3rswo2tn":true,"ee6snp15__s9n5gph0":true,"ee6snp15__e6x1kdqh":true,"treated_ee6snp15_yf4kqzht":true,"ee6snp15__hsquwpmj":true,"ee6snp15__9dj4q8g0":true,"ee6snp15__imxscsat":true,"ee6snp15__vz3zt0rg":true,"76kf3ans__507h6qdb":true,"76kf3ans__y66u2h7e":true,"76kf3ans__oijcz4e8":true,"76kf3ans__sdyxylhq":true,"76kf3ans__5oczvu25":true,"76kf3ans__npucjsxi":true,"treated_76kf3ans_32pzdqqp":true,"76kf3ans__5jixnhaz":true,"76kf3ans__4owexrnb":true,"76kf3ans__9hausbej":true,"76kf3ans__64yvr5uh":true,"76kf3ans__0h44m53n":true,"76kf3ans__a1t5kvrl":true,"76kf3ans__afwmc9g5":true,"76kf3ans__8c6yq3kg":true,"76kf3ans__898c7d5x":true,"76kf3ans__ejkd89o8":true,"treated_76kf3ans_2n64gszw":true,"76kf3ans__14gu1btu":true,"76kf3ans__k2h1nkw9":true,"treated_76kf3ans_bux35oit":true,"76kf3ans__9wrqnjc0":true,"76kf3ans__dkneh8h5":true,"76kf3ans__zfinlior":true,"treated_76kf3ans_drgof1xu":true,"76kf3ans__9dj4q8g0":true,"76kf3ans__imxscsat":true,"76kf3ans__vz3zt0rg":true,"76kf3ans__lq3lcyvh":true,"0aep7o37__y66u2h7e":true,"treated_0aep7o37_9hn1vj87":true,"0aep7o37__5jixnhaz":true,"0aep7o37__24qbxv18":true,"0aep7o37__crik6b73":true,"0aep7o37__4owexrnb":true,"0aep7o37__9hausbej":true,"0aep7o37__64yvr5uh":true,"0aep7o37__0h44m53n":true,"0aep7o37__a1t5kvrl":true,"0aep7o37__afwmc9g5":true,"0aep7o37__8c6yq3kg":true,"0aep7o37__898c7d5x":true,"0aep7o37__ejkd89o8":true,"0aep7o37__fhhx1cha":true,"0aep7o37__7hcfqp9x":true,"0aep7o37__ju3qxgji":true,"0aep7o37__14gu1btu":true,"0aep7o37__k2h1nkw9":true,"0aep7o37__ed8ag4zc":true,"treated_0aep7o37_bux35oit":true,"0aep7o37__pq8drcrt":true,"0aep7o37__8wqogyuv":true,"treated_0aep7o37_9tafd606":true,"0aep7o37__9wrqnjc0":true,"0aep7o37__zfinlior":true,"treated_0aep7o37_ok2syrrk":true,"0aep7o37__7juj0kaq":true,"0aep7o37__v1xk8bd9":true,"0aep7o37__0n6kn2mr":true,"0aep7o37__ard8clho":true,"0aep7o37__3rswo2tn":true,"0aep7o37__s9n5gph0":true,"0aep7o37__e6x1kdqh":true,"treated_0aep7o37_yf4kqzht":true,"0aep7o37__hsquwpmj":true,"0aep7o37__9dj4q8g0":true,"0aep7o37__imxscsat":true,"0aep7o37__vz3zt0rg":true,"0aep7o37__x625t430":true,"h42l60z5__5jixnhaz":true,"h42l60z5__24qbxv18":true,"h42l60z5__crik6b73":true,"h42l60z5__4owexrnb":true,"h42l60z5__9hausbej":true,"h42l60z5__64yvr5uh":true,"h42l60z5__0h44m53n":true,"h42l60z5__a1t5kvrl":true,"h42l60z5__afwmc9g5":true,"h42l60z5__898c7d5x":true,"h42l60z5__ejkd89o8":true,"h42l60z5__fhhx1cha":true,"h42l60z5__7hcfqp9x":true,"h42l60z5__ju3qxgji":true,"h42l60z5__14gu1btu":true,"h42l60z5__k2h1nkw9":true,"treated_h42l60z5_bux35oit":true,"h42l60z5__pq8drcrt":true,"h42l60z5__8wqogyuv":true,"h42l60z5__3u2k3d8x":true,"h42l60z5__9wrqnjc0":true,"h42l60z5__dkneh8h5":true,"h42l60z5__7juj0kaq":true,"h42l60z5__v1xk8bd9":true,"h42l60z5__0n6kn2mr":true,"h42l60z5__vvjmns3d":true,"h42l60z5__ard8clho":true,"h42l60z5__hhe8cy5u":true,"h42l60z5__3rswo2tn":true,"h42l60z5__s9n5gph0":true,"h42l60z5__e6x1kdqh":true,"h42l60z5__p66dcxec":true,"h42l60z5__hsquwpmj":true,"h42l60z5__ib2gyv7z":true,"h42l60z5__9dj4q8g0":true,"h42l60z5__imxscsat":true,"h42l60z5__vz3zt0rg":true,"c678r4v3__507h6qdb":true,"c678r4v3__y66u2h7e":true,"treated_c678r4v3_9hn1vj87":true,"c678r4v3__oijcz4e8":true,"c678r4v3__sdyxylhq":true,"c678r4v3__5oczvu25":true,"c678r4v3__npucjsxi":true,"c678r4v3__w6to2wwr":true,"c678r4v3__5jixnhaz":true,"c678r4v3__24qbxv18":true,"c678r4v3__crik6b73":true,"c678r4v3__4owexrnb":true,"c678r4v3__9hausbej":true,"c678r4v3__64yvr5uh":true,"c678r4v3__0h44m53n":true,"c678r4v3__a1t5kvrl":true,"c678r4v3__afwmc9g5":true,"c678r4v3__8c6yq3kg":true,"c678r4v3__898c7d5x":true,"c678r4v3__ejkd89o8":true,"c678r4v3__fhhx1cha":true,"c678r4v3__7hcfqp9x":true,"c678r4v3__ju3qxgji":true,"c678r4v3__14gu1btu":true,"c678r4v3__k2h1nkw9":true,"c678r4v3__ed8ag4zc":true,"c678r4v3__c1gvhv4o":true,"c678r4v3__pq8drcrt":true,"treated_c678r4v3_drgof1xu":true,"c678r4v3__v1xk8bd9":true,"c678r4v3__0n6kn2mr":true,"c678r4v3__vvjmns3d":true,"c678r4v3__ard8clho":true,"c678r4v3__ws8thypy":true,"c678r4v3__hhe8cy5u":true,"c678r4v3__3rswo2tn":true,"c678r4v3__s9n5gph0":true,"c678r4v3__e6x1kdqh":true,"c678r4v3__p66dcxec":true,"treated_c678r4v3_06nuka5q":true,"vuqxmzok__y66u2h7e":true,"vuqxmzok__oijcz4e8":true,"vuqxmzok__sdyxylhq":true,"treated_vuqxmzok_06nuka5q":true,"treated_vuqxmzok_0m5yzvkt":true,"vuqxmzok__5jixnhaz":true,"vuqxmzok__24qbxv18":true,"vuqxmzok__crik6b73":false,"vuqxmzok__9hausbej":true,"vuqxmzok__a1t5kvrl":true,"vuqxmzok__0h44m53n":true,"vuqxmzok__ju3qxgji":true,"vuqxmzok__14gu1btu":true,"vuqxmzok__9wrqnjc0":true,"vuqxmzok__dkneh8h5":true,"vuqxmzok__7juj0kaq":true,"treated_vuqxmzok_lxg44keb":true,"vuqxmzok__9dj4q8g0":true,"vuqxmzok__imxscsat":true,"vuqxmzok__vz3zt0rg":true,"vuqxmzok__x625t430":true,"treated_vuqxmzok_mpxhwmog":true,"treated_vuqxmzok_2bo8lpvg":true,"vuqxmzok__ys0ur3tq":true,"vuqxmzok__hmn1n910":true,"vuqxmzok__mei09vko":true,"vuqxmzok__lq3lcyvh":true,"w0yh056n__507h6qdb":true,"w0yh056n__y66u2h7e":true,"w0yh056n__lzhrlfua":true,"w0yh056n__wqz4usbe":true,"w0yh056n__47ljzdg8":true,"w0yh056n__oijcz4e8":true,"w0yh056n__sdyxylhq":true,"treated_w0yh056n_06nuka5q":true,"treated_w0yh056n_0m5yzvkt":true,"w0yh056n__w6to2wwr":true,"w0yh056n__1b57sf5o":true,"w0yh056n__24qbxv18":true,"w0yh056n__crik6b73":true,"w0yh056n__4owexrnb":true,"treated_w0yh056n_5vgh9ai4":true,"w0yh056n__898c7d5x":true,"w0yh056n__afwmc9g5":true,"w0yh056n__fhhx1cha":true,"w0yh056n__7hcfqp9x":true,"w0yh056n__14gu1btu":true,"w0yh056n__k2h1nkw9":true,"treated_w0yh056n_bux35oit":true,"w0yh056n__7juj0kaq":true,"w0yh056n__v1xk8bd9":true,"w0yh056n__0n6kn2mr":true,"w0yh056n__vvjmns3d":true,"w0yh056n__hhe8cy5u":true,"w0yh056n__3rswo2tn":true,"stino2h1__507h6qdb":true,"stino2h1__y66u2h7e":true,"stino2h1__oijcz4e8":true,"stino2h1__sdyxylhq":true,"treated_stino2h1_06nuka5q":true,"treated_stino2h1_0m5yzvkt":true,"stino2h1__w6to2wwr":true,"stino2h1__1b57sf5o":true,"stino2h1__5jixnhaz":true,"stino2h1__24qbxv18":true,"stino2h1__crik6b73":true,"stino2h1__4owexrnb":true,"stino2h1__9hausbej":true,"stino2h1__64yvr5uh":true,"stino2h1__0h44m53n":true,"stino2h1__a1t5kvrl":true,"stino2h1__afwmc9g5":true,"stino2h1__898c7d5x":true,"stino2h1__ejkd89o8":true,"stino2h1__fhhx1cha":true,"stino2h1__14gu1btu":true,"stino2h1__k2h1nkw9":true,"stino2h1__ju3qxgji":true,"treated_stino2h1_drgof1xu":true,"stino2h1__v1xk8bd9":true,"stino2h1__0n6kn2mr":true,"stino2h1__vvjmns3d":true,"stino2h1__ard8clho":true,"stino2h1__ws8thypy":true,"stino2h1__hhe8cy5u":true,"stino2h1__3rswo2tn":true,"stino2h1__s9n5gph0":true,"stino2h1__e6x1kdqh":true,"stino2h1__p66dcxec":true,"stino2h1__hsquwpmj":true,"stino2h1__ib2gyv7z":true,"stino2h1__9dj4q8g0":true,"stino2h1__imxscsat":true,"stino2h1__vz3zt0rg":true,"stino2h1__x625t430":true,"treated_a6ktjg7r_awsnqs09":true,"treated_a6ktjg7r_06nuka5q":true,"treated_a6ktjg7r_0m5yzvkt":true,"treated_a6ktjg7r_32pzdqqp":true,"a6ktjg7r__5jixnhaz":true,"a6ktjg7r__24qbxv18":true,"a6ktjg7r__crik6b73":true,"a6ktjg7r__4owexrnb":true,"a6ktjg7r__9hausbej":true,"a6ktjg7r__0h44m53n":true,"a6ktjg7r__a1t5kvrl":true,"a6ktjg7r__afwmc9g5":true,"a6ktjg7r__898c7d5x":true,"a6ktjg7r__fhhx1cha":true,"a6ktjg7r__14gu1btu":true,"a6ktjg7r__k2h1nkw9":true,"a6ktjg7r__ed8ag4zc":true,"a6ktjg7r__d8siusny":true,"a6ktjg7r__pq8drcrt":true,"a6ktjg7r__8wqogyuv":true,"treated_a6ktjg7r_9tafd606":true,"a6ktjg7r__9wrqnjc0":true,"a6ktjg7r__dkneh8h5":true,"a6ktjg7r__zfinlior":true,"treated_a6ktjg7r_drgof1xu":true,"a6ktjg7r__v1xk8bd9":true,"a6ktjg7r__0n6kn2mr":true,"a6ktjg7r__vvjmns3d":true,"a6ktjg7r__hhe8cy5u":true,"a6ktjg7r__3rswo2tn":true,"d8tahscw__507h6qdb":true,"d8tahscw__y66u2h7e":true,"d8tahscw__sdyxylhq":true,"treated_d8tahscw_drgof1xu":true,"d8tahscw__v1xk8bd9":true,"d8tahscw__0n6kn2mr":true,"d8tahscw__ard8clho":true,"d8tahscw__ws8thypy":true,"d8tahscw__hhe8cy5u":true,"d8tahscw__3rswo2tn":true,"d8tahscw__s9n5gph0":true,"d8tahscw__e6x1kdqh":true,"d8tahscw__p66dcxec":true,"d8tahscw__9dj4q8g0":true,"d8tahscw__5jixnhaz":true,"d8tahscw__24qbxv18":true,"d8tahscw__crik6b73":true,"d8tahscw__4owexrnb":true,"d8tahscw__9hausbej":true,"d8tahscw__64yvr5uh":true,"d8tahscw__0h44m53n":true,"d8tahscw__a1t5kvrl":true,"d8tahscw__afwmc9g5":true,"d8tahscw__8c6yq3kg":true,"d8tahscw__898c7d5x":true,"d8tahscw__ejkd89o8":true,"d8tahscw__fhhx1cha":true,"d8tahscw__ju3qxgji":true,"d8tahscw__14gu1btu":true,"d8tahscw__k2h1nkw9":true,"d8tahscw__8fkni8cd":true,"35x9q3wq__sdyxylhq":true,"35x9q3wq__5oczvu25":true,"35x9q3wq__5jixnhaz":true,"35x9q3wq__24qbxv18":true,"35x9q3wq__crik6b73":true,"35x9q3wq__4owexrnb":false,"35x9q3wq__9hausbej":true,"35x9q3wq__0h44m53n":true,"35x9q3wq__a1t5kvrl":true,"35x9q3wq__afwmc9g5":true,"35x9q3wq__ju3qxgji":true,"35x9q3wq__14gu1btu":true,"35x9q3wq__9wrqnjc0":true,"35x9q3wq__dkneh8h5":true,"35x9q3wq__zfinlior":true,"35x9q3wq__5w280aq9":false,"35x9q3wq__53xrkw14":true,"35x9q3wq__7juj0kaq":true,"35x9q3wq__v1xk8bd9":true,"35x9q3wq__0n6kn2mr":true,"pct0o65u__24qbxv18":true,"pct0o65u__crik6b73":true,"pct0o65u__4owexrnb":true,"pct0o65u__9hausbej":true,"pct0o65u__64yvr5uh":true,"pct0o65u__0h44m53n":true,"pct0o65u__a1t5kvrl":true,"treated_pct0o65u_ocfrtp1v":true,"pct0o65u__ju3qxgji":true,"pct0o65u__fhhx1cha":true,"treated_pct0o65u_ypsev6fy":true,"pct0o65u__c1gvhv4o":false,"treated_pct0o65u_bux35oit":true,"pct0o65u__9wrqnjc0":true,"treated_pct0o65u_55yukdid":true,"pct0o65u__sdyxylhq":true,"pct0o65u__5oczvu25":true,"pct0o65u__npucjsxi":true,"treated_pct0o65u_32pzdqqp":true,"pct0o65u__7juj0kaq":true,"pct0o65u__v1xk8bd9":true,"pct0o65u__0n6kn2mr":true,"pct0o65u__vvjmns3d":true,"pct0o65u__ard8clho":true,"pct0o65u__hhe8cy5u":true,"pct0o65u__3rswo2tn":true,"treated_pct0o65u_4daat3ry":true,"treated_pct0o65u_yf4kqzht":true,"pct0o65u__imxscsat":true,"pct0o65u__vz3zt0rg":true,"vx303o2a__24qbxv18":true,"vx303o2a__4owexrnb":true,"vx303o2a__9hausbej":true,"vx303o2a__64yvr5uh":true,"vx303o2a__0h44m53n":true,"vx303o2a__a1t5kvrl":true,"vx303o2a__afwmc9g5":true,"vx303o2a__8c6yq3kg":true,"vx303o2a__898c7d5x":true,"vx303o2a__ejkd89o8":true,"treated_vx303o2a_2n64gszw":true,"treated_vx303o2a_ypsev6fy":true,"treated_vx303o2a_55yukdid":true,"vx303o2a__oijcz4e8":true,"vx303o2a__sdyxylhq":true,"treated_vx303o2a_06nuka5q":true,"vx303o2a__5oczvu25":true,"vx303o2a__7juj0kaq":true,"vx303o2a__v1xk8bd9":true,"vx303o2a__0n6kn2mr":true,"vx303o2a__vvjmns3d":true,"vx303o2a__hhe8cy5u":true,"vx303o2a__3rswo2tn":true,"vx303o2a__s9n5gph0":true,"vx303o2a__e6x1kdqh":false,"vx303o2a__p66dcxec":true,"treated_vx303o2a_12g1ka58":true,"vx303o2a__imxscsat":true,"vx303o2a__vz3zt0rg":true,"vx303o2a__x625t430":true,"vx303o2a__4typ04yi":true,"vx303o2a__m0105u6a":true,"iotp3mj2__507h6qdb":true,"iotp3mj2__5jixnhaz":true,"iotp3mj2__crik6b73":true,"iotp3mj2__4owexrnb":true,"iotp3mj2__9hausbej":true,"iotp3mj2__64yvr5uh":true,"iotp3mj2__0h44m53n":true,"iotp3mj2__afwmc9g5":true,"iotp3mj2__898c7d5x":true,"iotp3mj2__ejkd89o8":true,"iotp3mj2__fhhx1cha":true,"iotp3mj2__7hcfqp9x":true,"iotp3mj2__14gu1btu":true,"iotp3mj2__k2h1nkw9":true,"iotp3mj2__ed8ag4zc":true,"treated_iotp3mj2_bux35oit":true,"iotp3mj2__pq8drcrt":true,"iotp3mj2__8wqogyuv":true,"treated_iotp3mj2_9tafd606":true,"iotp3mj2__9wrqnjc0":true,"iotp3mj2__dkneh8h5":true,"iotp3mj2__zfinlior":true,"iotp3mj2__53xrkw14":true,"iotp3mj2__y66u2h7e":true,"treated_iotp3mj2_9hn1vj87":true,"treated_iotp3mj2_awsnqs09":true,"treated_iotp3mj2_0m5yzvkt":true,"iotp3mj2__7juj0kaq":true,"iotp3mj2__v1xk8bd9":true,"iotp3mj2__0n6kn2mr":true,"iotp3mj2__vvjmns3d":true,"iotp3mj2__hhe8cy5u":true,"iotp3mj2__3rswo2tn":true,"iotp3mj2__s9n5gph0":true,"treated_iotp3mj2_yf4kqzht":true,"treated_iotp3mj2_12g1ka58":true,"iotp3mj2__imxscsat":true,"iotp3mj2__vz3zt0rg":true,"treated_iotp3mj2_mpxhwmog":true,"iotp3mj2__rbfwfsdw":true,"treated_iotp3mj2_l0tcopja":true,"ecoku53v__5jixnhaz":true,"ecoku53v__24qbxv18":true,"ecoku53v__4owexrnb":true,"ecoku53v__9hausbej":true,"ecoku53v__64yvr5uh":true,"ecoku53v__0h44m53n":true,"ecoku53v__a1t5kvrl":true,"ecoku53v__8c6yq3kg":true,"ecoku53v__898c7d5x":true,"ecoku53v__ejkd89o8":true,"ecoku53v__fhhx1cha":true,"ecoku53v__7hcfqp9x":true,"ecoku53v__14gu1btu":true,"ecoku53v__k2h1nkw9":true,"ecoku53v__ed8ag4zc":true,"treated_ecoku53v_bux35oit":true,"treated_ecoku53v_rokk8ye2":true,"ecoku53v__9wrqnjc0":true,"ecoku53v__dkneh8h5":true,"ecoku53v__zfinlior":true,"ecoku53v__53xrkw14":true,"treated_ecoku53v_drgof1xu":true,"ecoku53v__v1xk8bd9":true,"ecoku53v__ws8thypy":true,"ecoku53v__hhe8cy5u":true,"ecoku53v__3rswo2tn":true,"ecoku53v__s9n5gph0":true,"treated_ecoku53v_yf4kqzht":true,"treated_ecoku53v_12g1ka58":true,"ecoku53v__imxscsat":true,"ecoku53v__vz3zt0rg":true,"treated_ecoku53v_mpxhwmog":true,"treated_ecoku53v_2bo8lpvg":true,"55qn9jmx__5jixnhaz":true,"55qn9jmx__24qbxv18":true,"55qn9jmx__crik6b73":true,"55qn9jmx__9hausbej":true,"55qn9jmx__afwmc9g5":true,"treated_55qn9jmx_2n64gszw":true,"treated_55qn9jmx_ypsev6fy":true,"55qn9jmx__9wrqnjc0":true,"55qn9jmx__dkneh8h5":true,"55qn9jmx__zfinlior":true,"55qn9jmx__53xrkw14":true,"treated_55qn9jmx_awsnqs09":true,"treated_55qn9jmx_0m5yzvkt":true,"55qn9jmx__7juj0kaq":true,"55qn9jmx__v1xk8bd9":true,"55qn9jmx__0n6kn2mr":true,"55qn9jmx__vvjmns3d":true,"55qn9jmx__ard8clho":true,"55qn9jmx__hhe8cy5u":true,"55qn9jmx__3rswo2tn":true,"55qn9jmx__s9n5gph0":true,"55qn9jmx__e6x1kdqh":true,"55qn9jmx__p66dcxec":true,"55qn9jmx__uk5a5ojh":true,"55qn9jmx__hsquwpmj":true,"55qn9jmx__imxscsat":true,"55qn9jmx__vz3zt0rg":true,"treated_55qn9jmx_mpxhwmog":true,"0mqpz6ho__507h6qdb":true,"0mqpz6ho__y66u2h7e":false,"treated_0mqpz6ho_55yukdid":true,"0mqpz6ho__lzhrlfua":true,"treated_0mqpz6ho_awsnqs09":true,"0mqpz6ho__0eegwxql":true,"0mqpz6ho__5oczvu25":true,"0mqpz6ho__npucjsxi":true,"0mqpz6ho__w6to2wwr":true,"0mqpz6ho__5jixnhaz":true,"0mqpz6ho__24qbxv18":true,"0mqpz6ho__crik6b73":true,"0mqpz6ho__4owexrnb":true,"0mqpz6ho__9hausbej":true,"0mqpz6ho__0h44m53n":true,"0mqpz6ho__a1t5kvrl":true,"0mqpz6ho__afwmc9g5":true,"0mqpz6ho__8c6yq3kg":true,"0mqpz6ho__898c7d5x":true,"0mqpz6ho__ejkd89o8":true,"0mqpz6ho__fhhx1cha":true,"0mqpz6ho__14gu1btu":true,"treated_0mqpz6ho_bux35oit":true,"0mqpz6ho__9wrqnjc0":true,"0mqpz6ho__dkneh8h5":true,"treated_0mqpz6ho_yf6n8api":true,"0mqpz6ho__c4357fs1":true,"0mqpz6ho__53xrkw14":true,"treated_0mqpz6ho_drgof1xu":true,"0mqpz6ho__v1xk8bd9":true,"0mqpz6ho__0n6kn2mr":true,"0mqpz6ho__vvjmns3d":true,"0mqpz6ho__ard8clho":true,"0mqpz6ho__ws8thypy":true,"0mqpz6ho__hhe8cy5u":false,"0mqpz6ho__3rswo2tn":true,"0mqpz6ho__s9n5gph0":true,"0mqpz6ho__p66dcxec":true,"0mqpz6ho__hsquwpmj":true,"0mqpz6ho__imxscsat":true,"0mqpz6ho__vz3zt0rg":true,"0mqpz6ho__w4hfyxq0":true,"0mqpz6ho__x625t430":true,"0mqpz6ho__4typ04yi":true,"7r4x5hak__sdyxylhq":true,"treated_7r4x5hak_06nuka5q":true,"treated_7r4x5hak_0m5yzvkt":true,"treated_7r4x5hak_32pzdqqp":true,"7r4x5hak__24qbxv18":true,"7r4x5hak__crik6b73":true,"7r4x5hak__4owexrnb":true,"7r4x5hak__9hausbej":true,"7r4x5hak__fhhx1cha":true,"7r4x5hak__14gu1btu":true,"7r4x5hak__zfinlior":true,"treated_7r4x5hak_rokk8ye2":true,"7r4x5hak__7juj0kaq":true,"7r4x5hak__v1xk8bd9":true,"7r4x5hak__0n6kn2mr":true,"7r4x5hak__vvjmns3d":true,"7r4x5hak__ws8thypy":true,"7r4x5hak__hhe8cy5u":true,"7r4x5hak__3rswo2tn":true,"7r4x5hak__s9n5gph0":true,"treated_7r4x5hak_yf4kqzht":true,"treated_7r4x5hak_12g1ka58":true,"7r4x5hak__imxscsat":true,"7r4x5hak__vz3zt0rg":true,"ixx95kom__507h6qdb":true,"ixx95kom__y66u2h7e":true,"ixx95kom__24qbxv18":true,"ixx95kom__crik6b73":true,"ixx95kom__4owexrnb":true,"ixx95kom__9hausbej":true,"ixx95kom__64yvr5uh":true,"ixx95kom__0h44m53n":true,"ixx95kom__a1t5kvrl":true,"ixx95kom__afwmc9g5":true,"ixx95kom__8c6yq3kg":true,"ixx95kom__898c7d5x":true,"ixx95kom__ejkd89o8":true,"treated_ixx95kom_2n64gszw":true,"ixx95kom__14gu1btu":true,"ixx95kom__k2h1nkw9":true,"ixx95kom__ed8ag4zc":true,"ixx95kom__c1gvhv4o":true,"ixx95kom__d8siusny":true,"ixx95kom__3klmivf1":true,"ixx95kom__xg8nykmv":false,"ixx95kom__7juj0kaq":true,"ixx95kom__v1xk8bd9":true,"ixx95kom__0n6kn2mr":true,"ixx95kom__vvjmns3d":true,"ixx95kom__ard8clho":true,"ixx95kom__ws8thypy":true,"ixx95kom__hhe8cy5u":true,"ixx95kom__3rswo2tn":true,"ixx95kom__s9n5gph0":true,"ixx95kom__p66dcxec":false,"ixx95kom__9dj4q8g0":true,"treated_ixx95kom_yf4kqzht":true,"ixx95kom__imxscsat":true,"ixx95kom__vz3zt0rg":true,"treated_o00zbti8_awsnqs09":true,"o00zbti8__5oczvu25":true,"o00zbti8__npucjsxi":true,"o00zbti8__w6to2wwr":true,"o00zbti8__1b57sf5o":true,"o00zbti8__5jixnhaz":true,"o00zbti8__24qbxv18":true,"o00zbti8__crik6b73":true,"o00zbti8__4owexrnb":true,"o00zbti8__9hausbej":true,"treated_o00zbti8_ypsev6fy":true,"o00zbti8__pq8drcrt":true,"o00zbti8__8wqogyuv":true,"treated_o00zbti8_9tafd606":true,"o00zbti8__9wrqnjc0":true,"o00zbti8__dkneh8h5":true,"o00zbti8__zfinlior":true,"o00zbti8__7juj0kaq":true,"o00zbti8__v1xk8bd9":true,"o00zbti8__0n6kn2mr":true,"o00zbti8__vvjmns3d":true,"o00zbti8__ard8clho":true,"o00zbti8__hhe8cy5u":true,"o00zbti8__3rswo2tn":true,"o00zbti8__s9n5gph0":true,"o00zbti8__e6x1kdqh":true,"treated_o00zbti8_yf4kqzht":true,"o00zbti8__imxscsat":true,"o00zbti8__vz3zt0rg":true,"ipdq6d8w__5jixnhaz":true,"ipdq6d8w__crik6b73":true,"ipdq6d8w__4owexrnb":true,"ipdq6d8w__9hausbej":true,"ipdq6d8w__64yvr5uh":true,"ipdq6d8w__0h44m53n":true,"ipdq6d8w__a1t5kvrl":true,"ipdq6d8w__afwmc9g5":true,"ipdq6d8w__8c6yq3kg":true,"ipdq6d8w__898c7d5x":true,"ipdq6d8w__ejkd89o8":true,"ipdq6d8w__fhhx1cha":true,"ipdq6d8w__7hcfqp9x":true,"ipdq6d8w__ju3qxgji":true,"ipdq6d8w__14gu1btu":true,"treated_ipdq6d8w_bux35oit":true,"treated_ipdq6d8w_rokk8ye2":true,"treated_ipdq6d8w_9tafd606":true,"ipdq6d8w__9wrqnjc0":true,"ipdq6d8w__zfinlior":true,"treated_ipdq6d8w_ok2syrrk":true,"ipdq6d8w__oijcz4e8":true,"ipdq6d8w__sdyxylhq":true,"treated_ipdq6d8w_06nuka5q":true,"ipdq6d8w__5oczvu25":true,"ipdq6d8w__w6to2wwr":true,"treated_ipdq6d8w_drgof1xu":true,"ipdq6d8w__v1xk8bd9":true,"ipdq6d8w__0n6kn2mr":true,"ipdq6d8w__vvjmns3d":true,"ipdq6d8w__ard8clho":true,"ipdq6d8w__ws8thypy":true,"ipdq6d8w__hhe8cy5u":true,"ipdq6d8w__3rswo2tn":true,"ipdq6d8w__s9n5gph0":true,"treated_ipdq6d8w_yf4kqzht":true,"ipdq6d8w__p66dcxec":true,"ipdq6d8w__hsquwpmj":true,"ipdq6d8w__imxscsat":true,"ipdq6d8w__vz3zt0rg":true,"ipdq6d8w__w4hfyxq0":false,"ipdq6d8w__x625t430":true,"ipdq6d8w__4typ04yi":true,"ipdq6d8w__m0105u6a":true,"ipdq6d8w__rbfwfsdw":true,"ipdq6d8w__ys0ur3tq":true,"ipdq6d8w__lq3lcyvh":true,"ipdq6d8w__yg72hkp3":true,"ipdq6d8w__hmn1n910":true,"ipdq6d8w__mei09vko":true,"ttd3yvfv__5jixnhaz":true,"ttd3yvfv__crik6b73":true,"ttd3yvfv__4owexrnb":true,"ttd3yvfv__9hausbej":true,"ttd3yvfv__64yvr5uh":true,"ttd3yvfv__0h44m53n":true,"ttd3yvfv__a1t5kvrl":true,"treated_ttd3yvfv_2n64gszw":true,"ttd3yvfv__9wrqnjc0":true,"ttd3yvfv__dkneh8h5":true,"ttd3yvfv__sdyxylhq":true,"ttd3yvfv__0eegwxql":true,"ttd3yvfv__5oczvu25":true,"ttd3yvfv__npucjsxi":true,"ttd3yvfv__w6to2wwr":true,"ttd3yvfv__7juj0kaq":true,"ttd3yvfv__v1xk8bd9":true,"ttd3yvfv__0n6kn2mr":true,"ttd3yvfv__vvjmns3d":true,"ttd3yvfv__ws8thypy":true,"ttd3yvfv__hhe8cy5u":true,"ttd3yvfv__3rswo2tn":true,"treated_ttd3yvfv_4daat3ry":true,"ttd3yvfv__p66dcxec":true,"ttd3yvfv__uk5a5ojh":true,"ttd3yvfv__imxscsat":true,"ttd3yvfv__vz3zt0rg":true,"ttd3yvfv__4typ04yi":true,"ttd3yvfv__m0105u6a":true,"y95gn4y0__507h6qdb":true,"y95gn4y0__y66u2h7e":true,"treated_y95gn4y0_awsnqs09":true,"y95gn4y0__0eegwxql":true,"y95gn4y0__5oczvu25":false,"treated_y95gn4y0_0m5yzvkt":true,"treated_y95gn4y0_32pzdqqp":true,"y95gn4y0__5jixnhaz":true,"y95gn4y0__24qbxv18":true,"y95gn4y0__crik6b73":true,"y95gn4y0__4owexrnb":true,"y95gn4y0__9hausbej":true,"y95gn4y0__64yvr5uh":true,"y95gn4y0__0h44m53n":true,"y95gn4y0__a1t5kvrl":true,"y95gn4y0__afwmc9g5":true,"y95gn4y0__8c6yq3kg":true,"y95gn4y0__898c7d5x":true,"y95gn4y0__ejkd89o8":true,"y95gn4y0__fhhx1cha":true,"y95gn4y0__14gu1btu":true,"y95gn4y0__k2h1nkw9":true,"y95gn4y0__ed8ag4zc":true,"y95gn4y0__d8siusny":true,"y95gn4y0__8fkni8cd":true,"y95gn4y0__pq8drcrt":true,"y95gn4y0__8wqogyuv":true,"y95gn4y0__3u2k3d8x":true,"y95gn4y0__dkneh8h5":true,"y95gn4y0__9wrqnjc0":true,"treated_y95gn4y0_yf6n8api":true,"y95gn4y0__c4357fs1":true,"y95gn4y0__5w280aq9":true,"y95gn4y0__53xrkw14":true,"y95gn4y0__7juj0kaq":true,"y95gn4y0__0n6kn2mr":true,"y95gn4y0__vvjmns3d":true,"y95gn4y0__ard8clho":true,"y95gn4y0__ws8thypy":true,"y95gn4y0__hhe8cy5u":true,"y95gn4y0__3rswo2tn":true,"y95gn4y0__s9n5gph0":true,"y95gn4y0__p66dcxec":true,"y95gn4y0__hsquwpmj":true,"y95gn4y0__ib2gyv7z":true,"y95gn4y0__9dj4q8g0":true,"y95gn4y0__imxscsat":true,"y95gn4y0__vz3zt0rg":true,"y95gn4y0__x625t430":true,"y95gn4y0__4typ04yi":true,"y95gn4y0__m0105u6a":false,"y95gn4y0__rbfwfsdw":true,"treated_y95gn4y0_l0tcopja":true,"yo8bz0w6__9m22h4n6":true},"remarks":{"hx0ip34y__55yukdid":[],"hx0ip34y__9hn1vj87":[],"yo8bz0w6__9hn1vj87":["r","u"],"yo8bz0w6__drgof1xu":["r"],"yo8bz0w6__4daat3ry":["u"],"irk7ejyf__9hn1vj87":["u"],"irk7ejyf__06nuka5q":["r"],"irk7ejyf__0m5yzvkt":["!"],"irk7ejyf__32pzdqqp":["!"],"irk7ejyf__ypsev6fy":["r","!"],"irk7ejyf__sr75c1mm":["!"],"irk7ejyf__trysfn1h":["s"],"irk7ejyf__yf4kqzht":["r"],"irk7ejyf__mpxhwmog":["r"],"irk7ejyf__yf6n8api":[],"7z1c6b0p__9hn1vj87":["h"],"7z1c6b0p__4daat3ry":["u"],"pwjrbcey__sr75c1mm":["r"],"pwjrbcey__nktks2dc":["!"],"dvaud5yg__65g5k5eb":["r"],"dvaud5yg__4daat3ry":["r","u"],"7bilm4tk__2n64gszw":["r"],"7bilm4tk__drgof1xu":["r"],"tbfvcttu__awsnqs09":["r"],"tbfvcttu__0m5yzvkt":["r"],"7fk7lv49__9hn1vj87":[],"7fk7lv49__0m5yzvkt":["r"],"7fk7lv49__sr75c1mm":["r"],"7fk7lv49__rokk8ye2":["s"],"7fk7lv49__9tafd606":["s"],"7fk7lv49__trysfn1h":["r"],"7fk7lv49__12g1ka58":["r"],"cow5mnbu__4daat3ry":["u"],"ut7vpvl7__sr75c1mm":["r"],"ut7vpvl7__mpxhwmog":["r"],"qyk9hnyq__bux35oit":["h"],"qyk9hnyq__rokk8ye2":["r"],"qyk9hnyq__sr75c1mm":["r"],"qyk9hnyq__yf4kqzht":["r"],"qyk9hnyq__nktks2dc":["!"],"4wz55f5x__lxg44keb":["h"],"4wz55f5x__65g5k5eb":["r"],"4wz55f5x__4daat3ry":["u"],"4wz55f5x__nktks2dc":["h"],"4wz55f5x__mpxhwmog":["!"],"ibyliehb__9hn1vj87":[],"ibyliehb__0m5yzvkt":["!"],"ibyliehb__32pzdqqp":["!"],"ibyliehb__5vgh9ai4":["h","s"],"ibyliehb__ypsev6fy":["!","s"],"ibyliehb__trysfn1h":["!"],"ibyliehb__drgof1xu":["!"],"ibyliehb__lxg44keb":["!","h"],"ibyliehb__yf4kqzht":["!","h"],"iv3pn9eh__ypsev6fy":["!"],"iv3pn9eh__drgof1xu":["h"],"iv3pn9eh__lxg44keb":["s"],"gnrt0035__nwsf9pes":["r","h"],"gnrt0035__5vgh9ai4":["h"],"gnrt0035__ocfrtp1v":["r"],"gnrt0035__2n64gszw":["h"],"gnrt0035__ypsev6fy":["r","s"],"gnrt0035__sr75c1mm":["r"],"gnrt0035__drgof1xu":["r"],"gnrt0035__65g5k5eb":["r"],"fckepo2k__ypsev6fy":["!"],"fckepo2k__rokk8ye2":["r"],"fckepo2k__9tafd606":["r"],"h6u0fhb4__bux35oit":["r"],"50u2ckr0__nwsf9pes":["r"],"50u2ckr0__2n64gszw":["r"],"50u2ckr0__ypsev6fy":["!"],"50u2ckr0__sr75c1mm":["s"],"50u2ckr0__55yukdid":["r"],"50u2ckr0__0m5yzvkt":["r","s"],"50u2ckr0__32pzdqqp":["s","r"],"50u2ckr0__lxg44keb":["r"],"50u2ckr0__yf4kqzht":["r"],"lbo37lc6__9hn1vj87":["u","r"],"lbo37lc6__0m5yzvkt":["r"],"lbo37lc6__32pzdqqp":["r"],"lbo37lc6__nwsf9pes":["r"],"lbo37lc6__5vgh9ai4":["r"],"lbo37lc6__ocfrtp1v":["r"],"lbo37lc6__2n64gszw":["r"],"lbo37lc6__ypsev6fy":["r"],"lbo37lc6__sr75c1mm":["r"],"lbo37lc6__yf6n8api":["r"],"lbo37lc6__drgof1xu":["h"],"lbo37lc6__65g5k5eb":["r"],"lbo37lc6__yf4kqzht":["r"],"lbo37lc6__mpxhwmog":["r"],"ra1eyd6b__nwsf9pes":["r"],"ra1eyd6b__ypsev6fy":["h","!"],"ra1eyd6b__lxg44keb":["s"],"4pdli4fx__0m5yzvkt":[],"4pdli4fx__32pzdqqp":["r"],"4pdli4fx__ocfrtp1v":["!"],"4pdli4fx__ypsev6fy":["!"],"ee6snp15__4daat3ry":["r"],"ee6snp15__yf4kqzht":["r"],"ee6snp15__lxg44keb":["r"],"76kf3ans__nwsf9pes":["r"],"76kf3ans__5vgh9ai4":["r"],"76kf3ans__2n64gszw":[],"76kf3ans__yf6n8api":["r"],"76kf3ans__drgof1xu":["!"],"0aep7o37__2n64gszw":["r"],"0aep7o37__9tafd606":["r"],"0aep7o37__sr75c1mm":["r"],"0aep7o37__yf6n8api":[],"0aep7o37__lxg44keb":["r"],"0aep7o37__yf4kqzht":["!"],"h42l60z5__ypsev6fy":["!"],"h42l60z5__12g1ka58":["u"],"c678r4v3__drgof1xu":["h"],"vuqxmzok__nwsf9pes":["!"],"vuqxmzok__5vgh9ai4":["!"],"vuqxmzok__ypsev6fy":["!"],"vuqxmzok__12g1ka58":["u"],"stino2h1__awsnqs09":["r"],"stino2h1__0m5yzvkt":["r","s"],"stino2h1__32pzdqqp":["r","s"],"stino2h1__2n64gszw":["r"],"stino2h1__65g5k5eb":["s"],"stino2h1__yf4kqzht":["r"],"stino2h1__12g1ka58":["u"],"a6ktjg7r__0m5yzvkt":["!"],"a6ktjg7r__sr75c1mm":["r"],"a6ktjg7r__55yukdid":[],"a6ktjg7r__awsnqs09":["!"],"a6ktjg7r__32pzdqqp":["!"],"a6ktjg7r__5vgh9ai4":["h"],"a6ktjg7r__ocfrtp1v":["h"],"d8tahscw__12g1ka58":["u"],"d8tahscw__ypsev6fy":["!"],"35x9q3wq__nwsf9pes":["h"],"35x9q3wq__5vgh9ai4":["h"],"35x9q3wq__ocfrtp1v":["h"],"35x9q3wq__sr75c1mm":["r"],"35x9q3wq__trysfn1h":["!"],"pct0o65u__ocfrtp1v":["r"],"pct0o65u__2n64gszw":["r"],"pct0o65u__ypsev6fy":["!"],"pct0o65u__sr75c1mm":["r"],"pct0o65u__55yukdid":["r"],"pct0o65u__4daat3ry":["u"],"vx303o2a__5vgh9ai4":["r"],"vx303o2a__ypsev6fy":["!"],"vx303o2a__55yukdid":["r"],"vx303o2a__06nuka5q":["r"],"vx303o2a__4daat3ry":["u"],"vx303o2a__12g1ka58":["!"],"vx303o2a__mpxhwmog":["r"],"iotp3mj2__0m5yzvkt":["!"],"iotp3mj2__lxg44keb":["!"],"iotp3mj2__4daat3ry":["u"],"ecoku53v__4daat3ry":["u"],"ecoku53v__2bo8lpvg":["r"],"55qn9jmx__ocfrtp1v":["h"],"55qn9jmx__nwsf9pes":["h"],"55qn9jmx__2n64gszw":["h"],"55qn9jmx__ypsev6fy":["r"],"55qn9jmx__sr75c1mm":["r"],"55qn9jmx__4daat3ry":["r"],"55qn9jmx__12g1ka58":["u"],"55qn9jmx__mpxhwmog":["!"],"0mqpz6ho__ypsev6fy":["!"],"7r4x5hak__2n64gszw":["!"],"7r4x5hak__ypsev6fy":["!"],"7r4x5hak__yf4kqzht":["!"],"yo8bz0w6__55yukdid":[],"o00zbti8__32pzdqqp":[],"o00zbti8__0m5yzvkt":[],"o00zbti8__awsnqs09":["r"],"o00zbti8__ypsev6fy":["!"],"ipdq6d8w__ypsev6fy":["!","r"],"ipdq6d8w__bux35oit":["r"],"ipdq6d8w__mpxhwmog":["r"],"ipdq6d8w__2bo8lpvg":["r"],"ipdq6d8w__awsnqs09":["s"],"ipdq6d8w__32pzdqqp":["r","s"],"ttd3yvfv__2n64gszw":["!"],"y95gn4y0__awsnqs09":["!"],"y95gn4y0__ypsev6fy":["s"],"y95gn4y0__bux35oit":["s"],"y95gn4y0__sr75c1mm":["r"],"y95gn4y0__yf4kqzht":["s"],"y95gn4y0__12g1ka58":["u"]},"absents":{},"groupes":{"nsi":["ibyliehb","gnrt0035","w0yh056n","55qn9jmx","7r4x5hak","35x9q3wq","76kf3ans","ra1eyd6b","ee6snp15","ttd3yvfv","o00zbti8"],"grp_vgm3n":["ibyliehb","gnrt0035","o00zbti8","55qn9jmx","7r4x5hak","w0yh056n","ra1eyd6b","ee6snp15","76kf3ans","35x9q3wq","ttd3yvfv","h6u0fhb4"]},"activeExamId":"tdl4358z","nomDS":"DS 06","dateDS":"15 Avril 2026","seuils":{"nonNote":20,"D":25,"C":50,"B":75},"normMethod":"proportional_max","normParams":{"moyenneCible":9,"sigmaCible":3,"maxCible":16},"seuilDifficile":33,"seuilReussite":50,"gabaritTex":"\\documentclass[a4paper,12pt,twoside]{article}\n\\usepackage[top=2cm,bottom=1.4cm,left=1cm,right=1cm,headheight=20pt]{geometry}\n\\usepackage[utf8]{inputenc}\n\\usepackage[T1]{fontenc}\n\\usepackage[french]{babel}\n\\usepackage{lastpage}\n\\usepackage{graphicx}\n\\usepackage{amsmath}\n\\usepackage{amssymb}\n\\usepackage{array}\n\\usepackage{fancyhdr}\n\\usepackage[locale=FR]{siunitx}\n\\usepackage{multicol, multirow}\n\\usepackage{longtable}\n\\usepackage{tcolorbox}\n\\usepackage{libertine}\n\\usepackage{pgfplots}\n\\pgfplotsset{compat=newest}\n\n\\tcbset{\n  mybox/.style={colback=blue!10, colframe=black, boxrule=1pt, arc=4pt,\n    left=1pt, right=1pt, top=13pt, bottom=13pt}\n}\n\\tcbset{\n  mygbox/.style={colback=yellow!10, colframe=orange!10!yellow, boxrule=1pt, arc=4pt,\n    left=1pt, right=1pt, top=13pt, bottom=13pt}\n}\n\n\\pagestyle{fancy}\n\\fancyhf{}\n\\rfoot{DS 05 du 14 février 2026}\n\\lfoot{Lycée Joffre - MP2I - HX 232}\n\\renewcommand{\\headrulewidth}{1pt}\n\\renewcommand{\\footrulewidth}{1pt}\n\\setlength{\\headheight}{15pt}\n\\renewcommand{\\arraystretch}{1.2}\n\n\\begin{document}\n","malusPaliers":[{"seuil":5,"pct":5},{"seuil":10,"pct":10}],"malusMode":"apres","malusManuel":{},"uiScale":1.4,"appTheme":"light","groupesDef":[{"id":"grp_vgm3n","label":"NSI","color":"#2855a0","colorDark":"#5b9bd5","isStatGroup":true}],"commentaires":{},"remarquesActives":["r","h","u","s","!","custom_5jrvl"],"remarquesCustom":[{"id":"custom_5jrvl","label":"TEST","icon":"📌","malus":false}],"remarquesOrdre":[],"settingsTab":"export","csvConfig":{"sep":";","dec":",","cols":{"rang":true,"nom":true,"prenom":true,"absent":true,"note":true,"noteNorm":true,"groupe":false,"competences":false,"malus":false}},"htmlPresets":[{"name":"preset","config":{"noteBrute":false,"rang":true,"theme":"dark","competences":"radar","detailExercices":true,"histogramme":false,"statsClasse":{"moy":false,"sigma":false,"minMax":true},"noteNorm":true,"commentaire":false,"bareme":true}}],"htmlConfig":{"theme":"young","noteNorm":true,"noteBrute":false,"rang":true,"statsEleve":{"justesse":false,"efficacite":false,"malus":false},"statsClasse":{"moy":false,"minMax":false,"sigma":false},"competences":"grid","commentaire":false,"detailExercices":true,"bareme":false,"histogramme":true},"htmlStudentId":"yo8bz0w6","synthese":[{"examId":"tdl4358z","dsNom":"DS 05","dsDate":"14 février 2026","studentId":"yo8bz0w6","nom":"Collet","prenom":"Tristan","groupe":"","noteBrute":11.53,"noteNorm":16,"rang":1,"compA":"B","compN":"B","compR":"A","compV":"B"},{"examId":"tdl4358z","dsNom":"DS 05","dsDate":"14 février 2026","studentId":"irk7ejyf","nom":"Alliot","prenom":"Ewann","groupe":"","noteBrute":7.45,"noteNorm":9.81,"rang":15,"compA":"B","compN":"B","compR":"C","compV":"C"},{"examId":"tdl4358z","dsNom":"DS 05","dsDate":"14 février 2026","studentId":"7z1c6b0p","nom":"David","prenom":"Ruben","groupe":"","noteBrute":9.49,"noteNorm":13.16,"rang":3,"compA":"NN","compN":"A","compR":"A","compV":"A"},{"examId":"tdl4358z","dsNom":"DS 05","dsDate":"14 février 2026","studentId":"pwjrbcey","nom":"Amant","prenom":"Félix","groupe":"","noteBrute":8.61,"noteNorm":11.95,"rang":7,"compA":"B","compN":"B","compR":"B","compV":"B"},{"examId":"tdl4358z","dsNom":"DS 05","dsDate":"14 février 2026","studentId":"dvaud5yg","nom":"Sadeki","prenom":"Heni","groupe":"","noteBrute":5.55,"noteNorm":7.7,"rang":28,"compA":"C","compN":"B","compR":"C","compV":"C"},{"examId":"tdl4358z","dsNom":"DS 05","dsDate":"14 février 2026","studentId":"7bilm4tk","nom":"Oberlin","prenom":"Nathan","groupe":"","noteBrute":6.13,"noteNorm":8.51,"rang":23,"compA":"NN","compN":"A","compR":"B","compV":"A"},{"examId":"tdl4358z","dsNom":"DS 05","dsDate":"14 février 2026","studentId":"tbfvcttu","nom":"Lefèvre","prenom":"Maximilien","groupe":"","noteBrute":3.94,"noteNorm":5.47,"rang":39,"compA":"NN","compN":"B","compR":"B","compV":"A"},{"examId":"tdl4358z","dsNom":"DS 05","dsDate":"14 février 2026","studentId":"7fk7lv49","nom":"Delort","prenom":"Louis","groupe":"","noteBrute":8.03,"noteNorm":10.58,"rang":14,"compA":"B","compN":"B","compR":"B","compV":"B"},{"examId":"tdl4358z","dsNom":"DS 05","dsDate":"14 février 2026","studentId":"cow5mnbu","nom":"El Annaz","prenom":"Anis","groupe":"","noteBrute":8.47,"noteNorm":11.75,"rang":8,"compA":"A","compN":"B","compR":"B","compV":"B"},{"examId":"tdl4358z","dsNom":"DS 05","dsDate":"14 février 2026","studentId":"ut7vpvl7","nom":"Salatti","prenom":"Timéo","groupe":"","noteBrute":6.28,"noteNorm":8.71,"rang":22,"compA":"D","compN":"C","compR":"B","compV":"A"},{"examId":"tdl4358z","dsNom":"DS 05","dsDate":"14 février 2026","studentId":"qyk9hnyq","nom":"Lepéculier","prenom":"César","groupe":"","noteBrute":8.76,"noteNorm":12.15,"rang":5,"compA":"B","compN":"A","compR":"B","compV":"A"},{"examId":"tdl4358z","dsNom":"DS 05","dsDate":"14 février 2026","studentId":"4wz55f5x","nom":"Cerles","prenom":"Pablo","groupe":"","noteBrute":6.13,"noteNorm":8.51,"rang":24,"compA":"D","compN":"B","compR":"B","compV":"B"},{"examId":"tdl4358z","dsNom":"DS 05","dsDate":"14 février 2026","studentId":"ibyliehb","nom":"Cheung","prenom":"Chris","groupe":"NSI","noteBrute":3.65,"noteNorm":4.81,"rang":43,"compA":"D","compN":"C","compR":"C","compV":"C"},{"examId":"tdl4358z","dsNom":"DS 05","dsDate":"14 février 2026","studentId":"iv3pn9eh","nom":"Martin","prenom":"Lucas","groupe":"","noteBrute":5.11,"noteNorm":7.09,"rang":34,"compA":"C","compN":"B","compR":"C","compV":"C"},{"examId":"tdl4358z","dsNom":"DS 05","dsDate":"14 février 2026","studentId":"gnrt0035","nom":"Caplong","prenom":"Mathis","groupe":"NSI","noteBrute":4.53,"noteNorm":5.65,"rang":38,"compA":"NN","compN":"C","compR":"C","compV":"C"},{"examId":"tdl4358z","dsNom":"DS 05","dsDate":"14 février 2026","studentId":"fckepo2k","nom":"Duffault","prenom":"Oscar","groupe":"","noteBrute":8.18,"noteNorm":11.34,"rang":10,"compA":"NN","compN":"A","compR":"B","compV":"A"},{"examId":"tdl4358z","dsNom":"DS 05","dsDate":"14 février 2026","studentId":"h6u0fhb4","nom":"Singbo","prenom":"Yanis","groupe":"","noteBrute":6.86,"noteNorm":9.52,"rang":18,"compA":"NN","compN":"A","compR":"A","compV":"A"},{"examId":"tdl4358z","dsNom":"DS 05","dsDate":"14 février 2026","studentId":"50u2ckr0","nom":"Gimeno Limoni","prenom":"Tristan","groupe":"","noteBrute":9.05,"noteNorm":11.3,"rang":11,"compA":"A","compN":"B","compR":"B","compV":"A"},{"examId":"tdl4358z","dsNom":"DS 05","dsDate":"14 février 2026","studentId":"lbo37lc6","nom":"Laurent","prenom":"Clarence","groupe":"","noteBrute":10.07,"noteNorm":12.58,"rang":4,"compA":"B","compN":"A","compR":"A","compV":"B"},{"examId":"tdl4358z","dsNom":"DS 05","dsDate":"14 février 2026","studentId":"ra1eyd6b","nom":"Lahmani","prenom":"Bilal","groupe":"NSI","noteBrute":5.4,"noteNorm":7.49,"rang":30,"compA":"A","compN":"A","compR":"B","compV":"A"},{"examId":"tdl4358z","dsNom":"DS 05","dsDate":"14 février 2026","studentId":"4pdli4fx","nom":"Mehring","prenom":"Lirio","groupe":"","noteBrute":7.88,"noteNorm":10.94,"rang":13,"compA":"NN","compN":"B","compR":"B","compV":"B"},{"examId":"tdl4358z","dsNom":"DS 05","dsDate":"14 février 2026","studentId":"ee6snp15","nom":"Nebot","prenom":"Nathan","groupe":"NSI","noteBrute":3.94,"noteNorm":5.47,"rang":40,"compA":"B","compN":"B","compR":"C","compV":"B"},{"examId":"tdl4358z","dsNom":"DS 05","dsDate":"14 février 2026","studentId":"76kf3ans","nom":"Muhammad","prenom":"Daniel","groupe":"NSI","noteBrute":5.4,"noteNorm":7.49,"rang":31,"compA":"C","compN":"B","compR":"B","compV":"B"},{"examId":"tdl4358z","dsNom":"DS 05","dsDate":"14 février 2026","studentId":"0aep7o37","nom":"Malet","prenom":"Raphaël","groupe":"","noteBrute":7.01,"noteNorm":9.72,"rang":17,"compA":"A","compN":"B","compR":"B","compV":"B"},{"examId":"tdl4358z","dsNom":"DS 05","dsDate":"14 février 2026","studentId":"h42l60z5","nom":"Bance","prenom":"Arthur","groupe":"","noteBrute":6.86,"noteNorm":9.52,"rang":19,"compA":"B","compN":"A","compR":"B","compV":"A"},{"examId":"tdl4358z","dsNom":"DS 05","dsDate":"14 février 2026","studentId":"c678r4v3","nom":"Rougelot","prenom":"Rémi","groupe":"","noteBrute":8.03,"noteNorm":11.14,"rang":12,"compA":"NN","compN":"A","compR":"A","compV":"B"},{"examId":"tdl4358z","dsNom":"DS 05","dsDate":"14 février 2026","studentId":"vuqxmzok","nom":"Capallere","prenom":"Maxence","groupe":"","noteBrute":4.09,"noteNorm":5.67,"rang":37,"compA":"A","compN":"B","compR":"C","compV":"D"},{"examId":"tdl4358z","dsNom":"DS 05","dsDate":"14 février 2026","studentId":"w0yh056n","nom":"De Vos","prenom":"Wilhelm","groupe":"NSI","noteBrute":5.69,"noteNorm":7.9,"rang":27,"compA":"NN","compN":"A","compR":"C","compV":"A"},{"examId":"tdl4358z","dsNom":"DS 05","dsDate":"14 février 2026","studentId":"stino2h1","nom":"Egea","prenom":"Mathieu","groupe":"","noteBrute":7.45,"noteNorm":9.81,"rang":16,"compA":"B","compN":"A","compR":"B","compV":"A"},{"examId":"tdl4358z","dsNom":"DS 05","dsDate":"14 février 2026","studentId":"a6ktjg7r","nom":"Boukerroucha","prenom":"Ihab Ali","groupe":"","noteBrute":4.82,"noteNorm":6.68,"rang":35,"compA":"NN","compN":"C","compR":"C","compV":"B"},{"examId":"tdl4358z","dsNom":"DS 05","dsDate":"14 février 2026","studentId":"d8tahscw","nom":"Bendifallah","prenom":"Rayan","groupe":"","noteBrute":5.26,"noteNorm":7.29,"rang":33,"compA":"NN","compN":"B","compR":"B","compV":"A"},{"examId":"tdl4358z","dsNom":"DS 05","dsDate":"14 février 2026","studentId":"35x9q3wq","nom":"Linguet","prenom":"Emmanuel","groupe":"NSI","noteBrute":3.5,"noteNorm":4.86,"rang":42,"compA":"C","compN":"D","compR":"C","compV":"C"},{"examId":"tdl4358z","dsNom":"DS 05","dsDate":"14 février 2026","studentId":"pct0o65u","nom":"Aleksanyan","prenom":"Meri","groupe":"","noteBrute":4.09,"noteNorm":5.39,"rang":41,"compA":"B","compN":"C","compR":"C","compV":"C"},{"examId":"tdl4358z","dsNom":"DS 05","dsDate":"14 février 2026","studentId":"vx303o2a","nom":"Pouget","prenom":"Antoine","groupe":"","noteBrute":5.55,"noteNorm":7.31,"rang":32,"compA":"B","compN":"B","compR":"C","compV":"C"},{"examId":"tdl4358z","dsNom":"DS 05","dsDate":"14 février 2026","studentId":"iotp3mj2","nom":"Crisnaire","prenom":"Maxime","groupe":"","noteBrute":6.72,"noteNorm":9.32,"rang":20,"compA":"C","compN":"C","compR":"C","compV":"B"},{"examId":"tdl4358z","dsNom":"DS 05","dsDate":"14 février 2026","studentId":"ecoku53v","nom":"Bompard","prenom":"Nina","groupe":"","noteBrute":5.55,"noteNorm":7.7,"rang":29,"compA":"C","compN":"B","compR":"B","compV":"B"},{"examId":"tdl4358z","dsNom":"DS 05","dsDate":"14 février 2026","studentId":"55qn9jmx","nom":"Coralli","prenom":"Raphaël","groupe":"NSI","noteBrute":4.67,"noteNorm":6.16,"rang":36,"compA":"C","compN":"C","compR":"C","compV":"B"},{"examId":"tdl4358z","dsNom":"DS 05","dsDate":"14 février 2026","studentId":"0mqpz6ho","nom":"Julia","prenom":"Loris","groupe":"","noteBrute":8.76,"noteNorm":12.15,"rang":6,"compA":"B","compN":"B","compR":"B","compV":"B"},{"examId":"tdl4358z","dsNom":"DS 05","dsDate":"14 février 2026","studentId":"7r4x5hak","nom":"Coppi","prenom":"Luann-Nam","groupe":"NSI","noteBrute":3.21,"noteNorm":4.46,"rang":44,"compA":"B","compN":"C","compR":"C","compV":"B"},{"examId":"tdl4358z","dsNom":"DS 05","dsDate":"14 février 2026","studentId":"ixx95kom","nom":"Comallonga","prenom":"Eris","groupe":"","noteBrute":5.99,"noteNorm":8.3,"rang":25,"compA":"B","compN":"B","compR":"B","compV":"B"},{"examId":"tdl4358z","dsNom":"DS 05","dsDate":"14 février 2026","studentId":"o00zbti8","nom":"Bourlier","prenom":"Jaouën","groupe":"NSI","noteBrute":5.84,"noteNorm":8.1,"rang":26,"compA":"B","compN":"B","compR":"B","compV":"A"},{"examId":"tdl4358z","dsNom":"DS 05","dsDate":"14 février 2026","studentId":"ipdq6d8w","nom":"Garrigues","prenom":"Téofane","groupe":"","noteBrute":8.76,"noteNorm":11.54,"rang":9,"compA":"B","compN":"B","compR":"B","compV":"B"},{"examId":"tdl4358z","dsNom":"DS 05","dsDate":"14 février 2026","studentId":"ttd3yvfv","nom":"Nguyen","prenom":"Leny","groupe":"NSI","noteBrute":6.57,"noteNorm":9.11,"rang":21,"compA":"B","compN":"C","compR":"A","compV":"C"},{"examId":"tdl4358z","dsNom":"DS 05","dsDate":"14 février 2026","studentId":"y95gn4y0","nom":"de Colbert","prenom":"Baptiste","groupe":"","noteBrute":10.66,"noteNorm":14.05,"rang":2,"compA":"A","compN":"B","compR":"B","compV":"B"}],"etablissement":{"nom":"Lycée Joffre","classe":"MP2I","matricule":"HX VI","promotion":"232","anneeScolaire":"2024-2025"}}